{"pagination": {"count": 101}, "data": [{"flight_date": "2026-07-11", "flight_status": "scheduled", "departure": {"airport": "Zhengzhou", "timezone": "Asia/Shanghai", "iata": "CGO", "icao": "ZHCC", "terminal": null, "gate": null, "delay": null, "scheduled": "2026-07-11T17:00:00+00:00", "estimated": "2026-07-11T17:00:00+00:00", "actual": null, "estimated_runway": null, "actual_runway": null}, "arrival": {"airport": "Sofia", "timezone": "Europe/Sofia", "iata": "SOF", "icao": "LBSF", "terminal": null, "gate": null, "baggage": null, "scheduled": "2026-07-11T22:15:00+00:00", "delay": null, "estimated": null, "actual": null, "estimated_runway": null, "actual_runway": null}, "airline": {"name": "Compass Air Cargo", "iata": "HQ", "icao": "ADZ"}, "flight": {"number": "405", "iata": "HQ405", "icao": "ADZ405", "codeshared": null}, "aircraft": null, "live": null}, {"flight_date": "2026-07-10", "flight_status": "landed", "departure": {"airport": "Eindhoven", "timezone": "Europe/Amsterdam", "iata": "EIN", "icao": "EHEH", "terminal": null, "gate": "4", "delay": null, "scheduled": "2026-07-10T20:30:00+00:00", "estimated": "2026-07-10T20:30:00+00:00", "actual": "2026-07-10T20:50:00+00:00", "estimated_runway": "2026-07-10T20:50:00+00:00", "actual_runway": "2026-07-10T20:50:00+00:00"}, "arrival": {"airport": "Sofia", "timezone": "Europe/Sofia", "iata": "SOF", "icao": "LBSF", "terminal": "2", "gate": null, "baggage": "4", "scheduled": "2026-07-11T00:05:00+00:00", "delay": null, "estimated": "2026-07-10T23:58:00+00:00", "actual": "2026-07-10T23:53:00+00:00", "estimated_runway": "2026-07-10T23:53:00+00:00", "actual_runway": "2026-07-10T23:53:00+00:00"}, "airline": {"name": "Ryanair", "iata": "FR", "icao": "RYR"}, "flight": {"number": "6014", "iata": "FR6014", "icao": "RYR6014", "codeshared": null}, "aircraft": {"registration": null, "iata": null, "icao": null, "icao24": "48C234"}, "live": null}, {"flight_date": "2026-07-10", "flight_status": "landed", "departure": {"airport": "Bergamo - Orio al Serio", "timezone": "Europe/Rome", "iata": "BGY", "icao": "LIME", "terminal": null, "gate": null, "delay": null, "scheduled": "2026-07-10T21:10:00+00:00", "estimated": "2026-07-10T21:10:00+00:00", "actual": "2026-07-10T21:34:00+00:00", "estimated_runway": "2026-07-10T21:34:00+00:00", "actual_runway": "2026-07-10T21:34:00+00:00"}, "arrival": {"airport": "Sofia", "timezone": "Europe/Sofia", "iata": "SOF", "icao": "LBSF", "terminal": "1", "gate": null, "baggage": "1", "scheduled": "2026-07-11T00:10:00+00:00", "delay": null, "estimated": "2026-07-11T00:05:00+00:00", "actual": "2026-07-11T00:07:00+00:00", "estimated_runway": "2026-07-11T00:07:00+00:00", "actual_runway": "2026-07-11T00:07:00+00:00"}, "airline": {"name": "Wizz Air", "iata": "W6", "icao": "WZZ"}, "flight": {"number": "4390", "iata": "W64390", "icao": "WZZ4390", "codeshared": null}, "aircraft": {"registration": null, "iata": null, "icao": null, "icao24": "471F9A"}, "live": null}, {"flight_date": "2026-07-10", "flight_status": "scheduled", "departure": {"airport": "Berlin Brandenburg Airport", "timezone": "Europe/Berlin", "iata": "BER", "icao": "EDDB", "terminal": "2", "gate": "B30", "delay": 73, "scheduled": "2026-07-10T21:10:00+00:00", "estimated": "2026-07-10T21:10:00+00:00", "actual": "2026-07-10T22:55:00+00:00", "estimated_runway": "2026-07-10T22:55:00+00:00", "actual_runway": "2026-07-10T22:55:00+00:00"}, "arrival": {"airport": "Sofia", "timezone": "Europe/Sofia", "iata": "SOF", "icao": "LBSF", "terminal": "2", "gate": null, "baggage": "4", "scheduled": "2026-07-11T00:25:00+00:00", "delay": 73, "estimated": "2026-07-11T01:38:00+00:00", "actual": null, "estimated_runway": null, "actual_runway": null}, "airline": {"name": "Ryanair", "iata": "FR", "icao": "RYR"}, "flight": {"number": "1148", "iata": "FR1148", "icao": "RYR1148", "codeshared": null}, "aircraft": {"registration": null, "iata": null, "icao": null, "icao24": "48C121"}, "live": null}, {"flight_date": "2026-07-10", "flight_status": "landed", "departure": {"airport": "Larnaca", "timezone": "Asia/Nicosia", "iata": "LCA", "icao": "LCLK", "terminal": null, "gate": null, "delay": null, "scheduled": "2026-07-10T22:35:00+00:00", "estimated": "2026-07-10T22:35:00+00:00", "actual": "2026-07-10T22:45:00+00:00", "estimated_runway": "2026-07-10T22:45:00+00:00", "actual_runway": "2026-07-10T22:45:00+00:00"}, "arrival": {"airport": "Sofia", "timezone": "Europe/Sofia", "iata": "SOF", "icao": "LBSF", "terminal": "1", "gate": null, "baggage": "1", "scheduled": "2026-07-11T01:00:00+00:00", "delay": null, "estimated": "2026-07-11T00:40:00+00:00", "actual": "2026-07-11T00:41:00+00:00", "estimated_runway": "2026-07-11T00:41:00+00:00", "actual_runway": "2026-07-11T00:41:00+00:00"}, "airline": {"name": "Wizz Air", "iata": "W6", "icao": "WZZ"}, "flight": {"number": "4438", "iata": "W64438", "icao": "WZZ4438", "codeshared": null}, "aircraft": {"registration": null, "iata": null, "icao": null, "icao24": "4D2049"}, "live": null}, {"flight_date": "2026-07-10", "flight_status": "landed", "departure": {"airport": "Stansted", "timezone": "Europe/London", "iata": "STN", "icao": "EGSS", "terminal": null, "gate": "49", "delay": 24, "scheduled": "2026-07-10T20:00:00+00:00", "estimated": "2026-07-10T20:00:00+00:00", "actual": "2026-07-10T20:54:00+00:00", "estimated_runway": "2026-07-10T20:54:00+00:00", "actual_runway": "2026-07-10T20:54:00+00:00"}, "arrival": {"airport": "Sofia", "timezone": "Europe/Sofia", "iata": "SOF", "icao": "LBSF", "terminal": "2", "gate": null, "baggage": "3", "scheduled": "2026-07-11T01:00:00+00:00", "delay": 24, "estimated": "2026-07-11T01:23:00+00:00", "actual": "2026-07-11T01:24:00+00:00", "estimated_runway": "2026-07-11T01:24:00+00:00", "actual_runway": "2026-07-11T01:24:00+00:00"}, "airline": {"name": "Ryanair", "iata": "FR", "icao": "RYR"}, "flight": {"number": "1730", "iata": "FR1730", "icao": "RYR1730", "codeshared": null}, "aircraft": {"registration": null, "iata": null, "icao": null, "icao24": "48C228"}, "live": null}, {"flight_date": "2026-07-11", "flight_status": "active", "departure": {"airport": "Zhengzhou", "timezone": "Asia/Shanghai", "iata": "CGO", "icao": "ZHCC", "terminal": null, "gate": null, "delay": null, "scheduled": "2026-07-11T10:00:00+00:00", "estimated": "2026-07-11T10:00:00+00:00", "actual": null, "estimated_runway": null, "actual_runway": null}, "arrival": {"airport": "Sofia", "timezone": "Europe/Sofia", "iata": "SOF", "icao": "LBSF", "terminal": null, "gate": null, "baggage": null, "scheduled": "2026-07-12T01:00:00+00:00", "delay": null, "estimated": null, "actual": null, "estimated_runway": null, "actual_runway": null}, "airline": {"name": "Compass Air Cargo", "iata": "HQ", "icao": "ADZ"}, "flight": {"number": "404", "iata": "HQ404", "icao": "ADZ404", "codeshared": null}, "aircraft": null, "live": null}, {"flight_date": "2026-07-10", "flight_status": "landed", "departure": {"airport": "Bergamo - Orio al Serio", "timezone": "Europe/Rome", "iata": "BGY", "icao": "LIME", "terminal": null, "gate": "A2", "delay": 24, "scheduled": "2026-07-10T22:15:00+00:00", "estimated": "2026-07-10T22:15:00+00:00", "actual": "2026-07-10T23:07:00+00:00", "estimated_runway": "2026-07-10T23:07:00+00:00", "actual_runway": "2026-07-10T23:07:00+00:00"}, "arrival": {"airport": "Sofia", "timezone": "Europe/Sofia", "iata": "SOF", "icao": "LBSF", "terminal": "2", "gate": null, "baggage": "4", "scheduled": "2026-07-11T01:15:00+00:00", "delay": 24, "estimated": "2026-07-11T01:46:00+00:00", "actual": "2026-07-11T01:39:00+00:00", "estimated_runway": "2026-07-11T01:39:00+00:00", "actual_runway": "2026-07-11T01:39:00+00:00"}, "airline": {"name": "Ryanair", "iata": "FR", "icao": "RYR"}, "flight": {"number": "3437", "iata": "FR3437", "icao": "RYR3437", "codeshared": null}, "aircraft": {"registration": null, "iata": null, "icao": null, "icao24": "48C138"}, "live": null}, {"flight_date": "2026-07-10", "flight_status": "landed", "departure": {"airport": "Barajas", "timezone": "Europe/Madrid", "iata": "MAD", "icao": "LEMD", "terminal": "1", "gate": "D54", "delay": null, "scheduled": "2026-07-10T20:55:00+00:00", "estimated": "2026-07-10T20:55:00+00:00", "actual": "2026-07-10T21:16:00+00:00", "estimated_runway": "2026-07-10T21:16:00+00:00", "actual_runway": "2026-07-10T21:16:00+00:00"}, "arrival": {"airport": "Sofia", "timezone": "Europe/Sofia", "iata": "SOF", "icao": "LBSF", "terminal": "1", "gate": null, "baggage": "2", "scheduled": "2026-07-11T01:25:00+00:00", "delay": null, "estimated": "2026-07-11T01:08:00+00:00", "actual": "2026-07-11T01:10:00+00:00", "estimated_runway": "2026-07-11T01:10:00+00:00", "actual_runway": "2026-07-11T01:10:00+00:00"}, "airline": {"name": "Wizz Air", "iata": "W6", "icao": "WZZ"}, "flight": {"number": "4402", "iata": "W64402", "icao": "WZZ4402", "codeshared": null}, "aircraft": {"registration": null, "iata": null, "icao": null, "icao24": "471DB9"}, "live": null}, {"flight_date": "2026-07-10", "flight_status": "landed", "departure": {"airport": "El Prat De Llobregat", "timezone": "Europe/Madrid", "iata": "BCN", "icao": "LEBL", "terminal": "2", "gate": "R12", "delay": 9, "scheduled": "2026-07-10T21:35:00+00:00", "estimated": "2026-07-10T21:35:00+00:00", "actual": "2026-07-10T22:19:00+00:00", "estimated_runway": "2026-07-10T22:19:00+00:00", "actual_runway": "2026-07-10T22:19:00+00:00"}, "arrival": {"airport": "Sofia", "timezone": "Europe/Sofia", "iata": "SOF", "icao": "LBSF", "terminal": "1", "gate": null, "baggage": "1", "scheduled": "2026-07-11T01:35:00+00:00", "delay": 9, "estimated": "2026-07-11T01:43:00+00:00", "actual": "2026-07-11T01:44:00+00:00", "estimated_runway": "2026-07-11T01:44:00+00:00", "actual_runway": "2026-07-11T01:44:00+00:00"}, "airline": {"name": "Wizz Air", "iata": "W6", "icao": "WZZ"}, "flight": {"number": "4406", "iata": "W64406", "icao": "WZZ4406", "codeshared": null}, "aircraft": {"registration": null, "iata": null, "icao": null, "icao24": "4D2534"}, "live": null}, {"flight_date": "2026-07-10", "flight_status": "landed", "departure": {"airport": "Frederic Chopin", "timezone": "Europe/Warsaw", "iata": "WAW", "icao": "EPWA", "terminal": null, "gate": null, "delay": null, "scheduled": "2026-07-10T22:45:00+00:00", "estimated": "2026-07-10T22:45:00+00:00", "actual": "2026-07-10T23:02:00+00:00", "estimated_runway": "2026-07-10T23:02:00+00:00", "actual_runway": "2026-07-10T23:02:00+00:00"}, "arrival": {"airport": "Sofia", "timezone": "Europe/Sofia", "iata": "SOF", "icao": "LBSF", "terminal": "2", "gate": null, "baggage": "2", "scheduled": "2026-07-11T01:45:00+00:00", "delay": null, "estimated": "2026-07-11T01:27:00+00:00", "actual": "2026-07-11T01:29:00+00:00", "estimated_runway": "2026-07-11T01:29:00+00:00", "actual_runway": "2026-07-11T01:29:00+00:00"}, "airline": {"name": "LOT", "iata": "LO", "icao": "LOT"}, "flight": {"number": "635", "iata": "LO635", "icao": "LOT635", "codeshared": null}, "aircraft": {"registration": null, "iata": null, "icao": null, "icao24": "48AD10"}, "live": null}, {"flight_date": "2026-07-10", "flight_status": "landed", "departure": {"airport": "Frederic Chopin", "timezone": "Europe/Warsaw", "iata": "WAW", "icao": "EPWA", "terminal": null, "gate": null, "delay": null, "scheduled": "2026-07-10T22:45:00+00:00", "estimated": "2026-07-10T22:45:00+00:00", "actual": "2026-07-10T23:02:00+00:00", "estimated_runway": "2026-07-10T23:02:00+00:00", "actual_runway": "2026-07-10T23:02:00+00:00"}, "arrival": {"airport": "Sofia", "timezone": "Europe/Sofia", "iata": "SOF", "icao": "LBSF", "terminal": "2", "gate": null, "baggage": "2", "scheduled": "2026-07-11T01:45:00+00:00", "delay": null, "estimated": "2026-07-11T01:27:00+00:00", "actual": "2026-07-11T01:29:00+00:00", "estimated_runway": "2026-07-11T01:29:00+00:00", "actual_runway": "2026-07-11T01:29:00+00:00"}, "airline": {"name": "SAS", "iata": "SK", "icao": "SAS"}, "flight": {"number": "8196", "iata": "SK8196", "icao": "SAS8196", "codeshared": {"airline_name": "lot", "airline_iata": "lo", "airline_icao": "lot", "flight_number": "635", "flight_iata": "lo635", "flight_icao": "lot635"}}, "aircraft": {"registration": null, "iata": null, "icao": null, "icao24": "48AD10"}, "live": null}, {"flight_date": "2026-07-11", "flight_status": "active", "departure": {"airport": "Rinas Mother Teresa", "timezone": "Europe/Tirane", "iata": "TIA", "icao": "LATI", "terminal": null, "gate": null, "delay": null, "scheduled": "2026-07-11T00:00:00+00:00", "estimated": "2026-07-11T00:00:00+00:00", "actual": null, "estimated_runway": null, "actual_runway": null}, "arrival": {"airport": "Sofia", "timezone": "Europe/Sofia", "iata": "SOF", "icao": "LBSF", "terminal": null, "gate": null, "baggage": null, "scheduled": "2026-07-11T01:57:00+00:00", "delay": 10, "estimated": null, "actual": null, "estimated_runway": null, "actual_runway": null}, "airline": {"name": "Fly2Sky", "iata": "F6", "icao": "VAW"}, "flight": {"number": null, "iata": "F6", "icao": "VAW", "codeshared": null}, "aircraft": {"registration": null, "iata": null, "icao": null, "icao24": "45209C"}, "live": null}, {"flight_date": "2026-07-11", "flight_status": "landed", "departure": {"airport": "Rinas Mother Teresa", "timezone": "Europe/Tirane", "iata": "TIA", "icao": "LATI", "terminal": null, "gate": null, "delay": null, "scheduled": "2026-07-11T00:00:00+00:00", "estimated": "2026-07-11T00:00:00+00:00", "actual": "2026-07-11T00:08:00+00:00", "estimated_runway": "2026-07-11T00:08:00+00:00", "actual_runway": "2026-07-11T00:08:00+00:00"}, "arrival": {"airport": "Sofia", "timezone": "Europe/Sofia", "iata": "SOF", "icao": "LBSF", "terminal": null, "gate": null, "baggage": null, "scheduled": "2026-07-11T01:57:00+00:00", "delay": null, "estimated": "2026-07-11T01:47:00+00:00", "actual": "2026-07-11T01:47:00+00:00", "estimated_runway": "2026-07-11T01:47:00+00:00", "actual_runway": "2026-07-11T01:47:00+00:00"}, "airline": {"name": "Fly2Sky", "iata": "F6", "icao": "VAW"}, "flight": {"number": "852", "iata": "F6852", "icao": "VAW852", "codeshared": null}, "aircraft": {"registration": null, "iata": null, "icao": null, "icao24": "45209C"}, "live": null}, {"flight_date": "2026-07-11", "flight_status": "active", "departure": {"airport": "Lech Walesa", "timezone": "Europe/Warsaw", "iata": "GDN", "icao": "EPGD", "terminal": null, "gate": null, "delay": 36, "scheduled": "2026-07-11T02:30:00+00:00", "estimated": "2026-07-11T02:30:00+00:00", "actual": "2026-07-11T03:05:00+00:00", "estimated_runway": "2026-07-11T03:05:00+00:00", "actual_runway": "2026-07-11T03:05:00+00:00"}, "arrival": {"airport": "Sofia", "timezone": "Europe/Sofia", "iata": "SOF", "icao": "LBSF", "terminal": null, "gate": null, "baggage": null, "scheduled": "2026-07-11T05:32:00+00:00", "delay": 36, "estimated": "2026-07-11T06:08:00+00:00", "actual": null, "estimated_runway": null, "actual_runway": null}, "airline": {"name": "Wizz Air", "iata": "W6", "icao": "WZZ"}, "flight": {"number": null, "iata": "W6", "icao": "WZZ", "codeshared": null}, "aircraft": {"registration": null, "iata": null, "icao": null, "icao24": "4D2424"}, "live": null}, {"flight_date": "2026-07-11", "flight_status": "landed", "departure": {"airport": "Malta International", "timezone": "Europe/Malta", "iata": "MLA", "icao": "LMML", "terminal": null, "gate": "4", "delay": null, "scheduled": "2026-07-11T05:50:00+00:00", "estimated": "2026-07-11T05:50:00+00:00", "actual": "2026-07-11T05:50:00+00:00", "estimated_runway": "2026-07-11T05:50:00+00:00", "actual_runway": "2026-07-11T05:50:00+00:00"}, "arrival": {"airport": "Sofia", "timezone": "Europe/Sofia", "iata": "SOF", "icao": "LBSF", "terminal": "2", "gate": null, "baggage": "4", "scheduled": "2026-07-11T08:40:00+00:00", "delay": null, "estimated": "2026-07-11T08:17:00+00:00", "actual": "2026-07-11T08:17:00+00:00", "estimated_runway": "2026-07-11T08:17:00+00:00", "actual_runway": "2026-07-11T08:17:00+00:00"}, "airline": {"name": "Ryanair", "iata": "FR", "icao": "RYR"}, "flight": {"number": "3833", "iata": "FR3833", "icao": "RYR3833", "codeshared": null}, "aircraft": {"registration": null, "iata": null, "icao": null, "icao24": "4CAD39"}, "live": null}, {"flight_date": "2026-07-11", "flight_status": "landed", "departure": {"airport": "Halle", "timezone": "Europe/Berlin", "iata": "LEJ", "icao": "EDDP", "terminal": null, "gate": null, "delay": 3, "scheduled": "2026-07-11T05:40:00+00:00", "estimated": "2026-07-11T05:40:00+00:00", "actual": "2026-07-11T06:02:00+00:00", "estimated_runway": "2026-07-11T06:02:00+00:00", "actual_runway": "2026-07-11T06:02:00+00:00"}, "arrival": {"airport": "Sofia", "timezone": "Europe/Sofia", "iata": "SOF", "icao": "LBSF", "terminal": null, "gate": null, "baggage": null, "scheduled": "2026-07-11T08:40:00+00:00", "delay": 3, "estimated": "2026-07-11T08:41:00+00:00", "actual": "2026-07-11T08:43:00+00:00", "estimated_runway": "2026-07-11T08:43:00+00:00", "actual_runway": "2026-07-11T08:43:00+00:00"}, "airline": {"name": "DHL Air", "iata": "D0", "icao": "DHK"}, "flight": {"number": "9008", "iata": "D09008", "icao": "DHK9008", "codeshared": null}, "aircraft": {"registration": null, "iata": null, "icao": null, "icao24": "4520F9"}, "live": null}, {"flight_date": "2026-07-11", "flight_status": "landed", "departure": {"airport": "Istanbul Airport", "timezone": "Europe/Istanbul", "iata": "IST", "icao": "LTFM", "terminal": null, "gate": "B9B", "delay": null, "scheduled": "2026-07-11T07:30:00+00:00", "estimated": "2026-07-11T07:30:00+00:00", "actual": "2026-07-11T07:42:00+00:00", "estimated_runway": "2026-07-11T07:42:00+00:00", "actual_runway": "2026-07-11T07:42:00+00:00"}, "arrival": {"airport": "Sofia", "timezone": "Europe/Sofia", "iata": "SOF", "icao": "LBSF", "terminal": "2", "gate": null, "baggage": "2", "scheduled": "2026-07-11T08:45:00+00:00", "delay": null, "estimated": "2026-07-11T08:28:00+00:00", "actual": "2026-07-11T08:30:00+00:00", "estimated_runway": "2026-07-11T08:30:00+00:00", "actual_runway": "2026-07-11T08:30:00+00:00"}, "airline": {"name": "Egyptair", "iata": "MS", "icao": "MSR"}, "flight": {"number": "9667", "iata": "MS9667", "icao": "MSR9667", "codeshared": {"airline_name": "turkish airlines", "airline_iata": "tk", "airline_icao": "thy", "flight_number": "1027", "flight_iata": "tk1027", "flight_icao": "thy1027"}}, "aircraft": {"registration": null, "iata": null, "icao": null, "icao24": "4BAA53"}, "live": null}, {"flight_date": "2026-07-11", "flight_status": "landed", "departure": {"airport": "Istanbul Airport", "timezone": "Europe/Istanbul", "iata": "IST", "icao": "LTFM", "terminal": null, "gate": "B9B", "delay": null, "scheduled": "2026-07-11T07:30:00+00:00", "estimated": "2026-07-11T07:30:00+00:00", "actual": "2026-07-11T07:42:00+00:00", "estimated_runway": "2026-07-11T07:42:00+00:00", "actual_runway": "2026-07-11T07:42:00+00:00"}, "arrival": {"airport": "Sofia", "timezone": "Europe/Sofia", "iata": "SOF", "icao": "LBSF", "terminal": "2", "gate": null, "baggage": "2", "scheduled": "2026-07-11T08:45:00+00:00", "delay": null, "estimated": "2026-07-11T08:28:00+00:00", "actual": "2026-07-11T08:30:00+00:00", "estimated_runway": "2026-07-11T08:30:00+00:00", "actual_runway": "2026-07-11T08:30:00+00:00"}, "airline": {"name": "IndiGo", "iata": "6E", "icao": "IGO"}, "flight": {"number": "4123", "iata": "6E4123", "icao": "IGO4123", "codeshared": {"airline_name": "turkish airlines", "airline_iata": "tk", "airline_icao": "thy", "flight_number": "1027", "flight_iata": "tk1027", "flight_icao": "thy1027"}}, "aircraft": {"registration": null, "iata": null, "icao": null, "icao24": "4BAA53"}, "live": null}, {"flight_date": "2026-07-11", "flight_status": "landed", "departure": {"airport": "Istanbul Airport", "timezone": "Europe/Istanbul", "iata": "IST", "icao": "LTFM", "terminal": null, "gate": "B9B", "delay": null, "scheduled": "2026-07-11T07:30:00+00:00", "estimated": "2026-07-11T07:30:00+00:00", "actual": "2026-07-11T07:42:00+00:00", "estimated_runway": "2026-07-11T07:42:00+00:00", "actual_runway": "2026-07-11T07:42:00+00:00"}, "arrival": {"airport": "Sofia", "timezone": "Europe/Sofia", "iata": "SOF", "icao": "LBSF", "terminal": "2", "gate": null, "baggage": "2", "scheduled": "2026-07-11T08:45:00+00:00", "delay": null, "estimated": "2026-07-11T08:28:00+00:00", "actual": "2026-07-11T08:30:00+00:00", "estimated_runway": "2026-07-11T08:30:00+00:00", "actual_runway": "2026-07-11T08:30:00+00:00"}, "airline": {"name": "Turkish Airlines", "iata": "TK", "icao": "THY"}, "flight": {"number": "1027", "iata": "TK1027", "icao": "THY1027", "codeshared": null}, "aircraft": {"registration": null, "iata": null, "icao": null, "icao24": "4BAA53"}, "live": null}, {"flight_date": "2026-07-11", "flight_status": "landed", "departure": {"airport": "Skiathos", "timezone": "Europe/Athens", "iata": "JSI", "icao": "LGSK", "terminal": null, "gate": "3", "delay": null, "scheduled": "2026-07-11T08:00:00+00:00", "estimated": "2026-07-11T08:00:00+00:00", "actual": "2026-07-11T08:09:00+00:00", "estimated_runway": "2026-07-11T08:09:00+00:00", "actual_runway": "2026-07-11T08:09:00+00:00"}, "arrival": {"airport": "Sofia", "timezone": "Europe/Sofia", "iata": "SOF", "icao": "LBSF", "terminal": "2", "gate": null, "baggage": "3", "scheduled": "2026-07-11T09:05:00+00:00", "delay": null, "estimated": "2026-07-11T08:52:00+00:00", "actual": "2026-07-11T08:48:00+00:00", "estimated_runway": "2026-07-11T08:48:00+00:00", "actual_runway": "2026-07-11T08:48:00+00:00"}, "airline": {"name": "Ryanair", "iata": "FR", "icao": "RYR"}, "flight": {"number": "4790", "iata": "FR4790", "icao": "RYR4790", "codeshared": null}, "aircraft": {"registration": null, "iata": null, "icao": null, "icao24": "48C138"}, "live": null}, {"flight_date": "2026-07-11", "flight_status": "active", "departure": {"airport": "Frederic Chopin", "timezone": "Europe/Warsaw", "iata": "WAW", "icao": "EPWA", "terminal": null, "gate": null, "delay": null, "scheduled": "2026-07-11T06:30:00+00:00", "estimated": "2026-07-11T06:30:00+00:00", "actual": "2026-07-11T06:43:00+00:00", "estimated_runway": "2026-07-11T06:43:00+00:00", "actual_runway": "2026-07-11T06:43:00+00:00"}, "arrival": {"airport": "Sofia", "timezone": "Europe/Sofia", "iata": "SOF", "icao": "LBSF", "terminal": "1", "gate": null, "baggage": "1", "scheduled": "2026-07-11T09:25:00+00:00", "delay": 13, "estimated": "2026-07-11T09:17:00+00:00", "actual": null, "estimated_runway": null, "actual_runway": null}, "airline": {"name": "Wizz Air", "iata": "W6", "icao": "WZZ"}, "flight": {"number": "4348", "iata": "W64348", "icao": "WZZ4348", "codeshared": null}, "aircraft": {"registration": null, "iata": null, "icao": null, "icao24": "471FA1"}, "live": null}, {"flight_date": "2026-07-11", "flight_status": "landed", "departure": {"airport": "Henri Coanda International", "timezone": "Europe/Bucharest", "iata": "OTP", "icao": "LROP", "terminal": null, "gate": null, "delay": null, "scheduled": "2026-07-11T08:20:00+00:00", "estimated": "2026-07-11T08:20:00+00:00", "actual": "2026-07-11T08:27:00+00:00", "estimated_runway": "2026-07-11T08:27:00+00:00", "actual_runway": "2026-07-11T08:27:00+00:00"}, "arrival": {"airport": "Sofia", "timezone": "Europe/Sofia", "iata": "SOF", "icao": "LBSF", "terminal": "2", "gate": null, "baggage": "2", "scheduled": "2026-07-11T09:35:00+00:00", "delay": null, "estimated": "2026-07-11T09:18:00+00:00", "actual": "2026-07-11T09:19:00+00:00", "estimated_runway": "2026-07-11T09:19:00+00:00", "actual_runway": "2026-07-11T09:19:00+00:00"}, "airline": {"name": "Tarom", "iata": "RO", "icao": "ROT"}, "flight": {"number": "291", "iata": "RO291", "icao": "ROT291", "codeshared": null}, "aircraft": {"registration": null, "iata": null, "icao": null, "icao24": "4A068D"}, "live": null}, {"flight_date": "2026-07-11", "flight_status": "landed", "departure": {"airport": "Henri Coanda International", "timezone": "Europe/Bucharest", "iata": "OTP", "icao": "LROP", "terminal": null, "gate": null, "delay": null, "scheduled": "2026-07-11T08:20:00+00:00", "estimated": "2026-07-11T08:20:00+00:00", "actual": "2026-07-11T08:27:00+00:00", "estimated_runway": "2026-07-11T08:27:00+00:00", "actual_runway": "2026-07-11T08:27:00+00:00"}, "arrival": {"airport": "Sofia", "timezone": "Europe/Sofia", "iata": "SOF", "icao": "LBSF", "terminal": "2", "gate": null, "baggage": "2", "scheduled": "2026-07-11T09:35:00+00:00", "delay": null, "estimated": "2026-07-11T09:18:00+00:00", "actual": "2026-07-11T09:19:00+00:00", "estimated_runway": "2026-07-11T09:19:00+00:00", "actual_runway": "2026-07-11T09:19:00+00:00"}, "airline": {"name": "Air France", "iata": "AF", "icao": "AFR"}, "flight": {"number": "6623", "iata": "AF6623", "icao": "AFR6623", "codeshared": {"airline_name": "tarom", "airline_iata": "ro", "airline_icao": "rot", "flight_number": "291", "flight_iata": "ro291", "flight_icao": "rot291"}}, "aircraft": {"registration": null, "iata": null, "icao": null, "icao24": "4A068D"}, "live": null}, {"flight_date": "2026-07-11", "flight_status": "landed", "departure": {"airport": "Henri Coanda International", "timezone": "Europe/Bucharest", "iata": "OTP", "icao": "LROP", "terminal": null, "gate": null, "delay": null, "scheduled": "2026-07-11T08:20:00+00:00", "estimated": "2026-07-11T08:20:00+00:00", "actual": "2026-07-11T08:27:00+00:00", "estimated_runway": "2026-07-11T08:27:00+00:00", "actual_runway": "2026-07-11T08:27:00+00:00"}, "arrival": {"airport": "Sofia", "timezone": "Europe/Sofia", "iata": "SOF", "icao": "LBSF", "terminal": "2", "gate": null, "baggage": "2", "scheduled": "2026-07-11T09:35:00+00:00", "delay": null, "estimated": "2026-07-11T09:18:00+00:00", "actual": "2026-07-11T09:19:00+00:00", "estimated_runway": "2026-07-11T09:19:00+00:00", "actual_runway": "2026-07-11T09:19:00+00:00"}, "airline": {"name": "Bulgaria Air", "iata": "FB", "icao": "LZB"}, "flight": {"number": "1806", "iata": "FB1806", "icao": "LZB1806", "codeshared": {"airline_name": "tarom", "airline_iata": "ro", "airline_icao": "rot", "flight_number": "291", "flight_iata": "ro291", "flight_icao": "rot291"}}, "aircraft": {"registration": null, "iata": null, "icao": null, "icao24": "4A068D"}, "live": null}, {"flight_date": "2026-07-11", "flight_status": "active", "departure": {"airport": "Rinas Mother Teresa", "timezone": "Europe/Tirane", "iata": "TIA", "icao": "LATI", "terminal": null, "gate": null, "delay": null, "scheduled": "2026-07-11T07:40:00+00:00", "estimated": "2026-07-11T07:40:00+00:00", "actual": "2026-07-11T07:50:00+00:00", "estimated_runway": "2026-07-11T07:50:00+00:00", "actual_runway": "2026-07-11T07:50:00+00:00"}, "arrival": {"airport": "Sofia", "timezone": "Europe/Sofia", "iata": "SOF", "icao": "LBSF", "terminal": "1", "gate": null, "baggage": "2", "scheduled": "2026-07-11T09:40:00+00:00", "delay": 11, "estimated": "2026-07-11T09:29:00+00:00", "actual": null, "estimated_runway": null, "actual_runway": null}, "airline": {"name": "Wizz Air", "iata": "W6", "icao": "WZZ"}, "flight": {"number": "4392", "iata": "W64392", "icao": "WZZ4392", "codeshared": null}, "aircraft": {"registration": null, "iata": null, "icao": null, "icao24": "4D2424"}, "live": null}, {"flight_date": "2026-07-11", "flight_status": "active", "departure": {"airport": "Bergamo - Orio al Serio", "timezone": "Europe/Rome", "iata": "BGY", "icao": "LIME", "terminal": null, "gate": "A6", "delay": null, "scheduled": "2026-07-11T06:45:00+00:00", "estimated": "2026-07-11T06:45:00+00:00", "actual": "2026-07-11T06:54:00+00:00", "estimated_runway": "2026-07-11T06:54:00+00:00", "actual_runway": "2026-07-11T06:54:00+00:00"}, "arrival": {"airport": "Sofia", "timezone": "Europe/Sofia", "iata": "SOF", "icao": "LBSF", "terminal": "2", "gate": null, "baggage": "4", "scheduled": "2026-07-11T09:45:00+00:00", "delay": 9, "estimated": "2026-07-11T09:30:00+00:00", "actual": null, "estimated_runway": null, "actual_runway": null}, "airline": {"name": "Ryanair", "iata": "FR", "icao": "RYR"}, "flight": {"number": "3400", "iata": "FR3400", "icao": "RYR3400", "codeshared": null}, "aircraft": {"registration": null, "iata": null, "icao": null, "icao24": "4CADA4"}, "live": null}, {"flight_date": "2026-07-11", "flight_status": "active", "departure": {"airport": "Athens International Airport \"Eleftherios Venizelos\"", "timezone": "Europe/Athens", "iata": "ATH", "icao": "LGAV", "terminal": "M", "gate": "B29", "delay": null, "scheduled": "2026-07-11T08:50:00+00:00", "estimated": "2026-07-11T08:50:00+00:00", "actual": "2026-07-11T09:06:00+00:00", "estimated_runway": "2026-07-11T09:06:00+00:00", "actual_runway": "2026-07-11T09:06:00+00:00"}, "arrival": {"airport": "Sofia", "timezone": "Europe/Sofia", "iata": "SOF", "icao": "LBSF", "terminal": "2", "gate": null, "baggage": "2", "scheduled": "2026-07-11T10:05:00+00:00", "delay": 17, "estimated": "2026-07-11T10:00:00+00:00", "actual": null, "estimated_runway": null, "actual_runway": null}, "airline": {"name": "Bulgaria Air", "iata": "FB", "icao": "LZB"}, "flight": {"number": "1506", "iata": "FB1506", "icao": "LZB1506", "codeshared": {"airline_name": "aegean airlines", "airline_iata": "a3", "airline_icao": "aee", "flight_number": "980", "flight_iata": "a3980", "flight_icao": "aee980"}}, "aircraft": {"registration": null, "iata": null, "icao": null, "icao24": "4692D9"}, "live": null}, {"flight_date": "2026-07-11", "flight_status": "active", "departure": {"airport": "Athens International Airport \"Eleftherios Venizelos\"", "timezone": "Europe/Athens", "iata": "ATH", "icao": "LGAV", "terminal": "M", "gate": "B29", "delay": null, "scheduled": "2026-07-11T08:50:00+00:00", "estimated": "2026-07-11T08:50:00+00:00", "actual": "2026-07-11T09:06:00+00:00", "estimated_runway": "2026-07-11T09:06:00+00:00", "actual_runway": "2026-07-11T09:06:00+00:00"}, "arrival": {"airport": "Sofia", "timezone": "Europe/Sofia", "iata": "SOF", "icao": "LBSF", "terminal": "2", "gate": null, "baggage": "2", "scheduled": "2026-07-11T10:05:00+00:00", "delay": 17, "estimated": "2026-07-11T10:00:00+00:00", "actual": null, "estimated_runway": null, "actual_runway": null}, "airline": {"name": "airBaltic", "iata": "BT", "icao": "BTI"}, "flight": {"number": "5457", "iata": "BT5457", "icao": "BTI5457", "codeshared": {"airline_name": "aegean airlines", "airline_iata": "a3", "airline_icao": "aee", "flight_number": "980", "flight_iata": "a3980", "flight_icao": "aee980"}}, "aircraft": {"registration": null, "iata": null, "icao": null, "icao24": "4692D9"}, "live": null}, {"flight_date": "2026-07-11", "flight_status": "active", "departure": {"airport": "Athens International Airport \"Eleftherios Venizelos\"", "timezone": "Europe/Athens", "iata": "ATH", "icao": "LGAV", "terminal": "M", "gate": "B29", "delay": null, "scheduled": "2026-07-11T08:50:00+00:00", "estimated": "2026-07-11T08:50:00+00:00", "actual": "2026-07-11T09:06:00+00:00", "estimated_runway": "2026-07-11T09:06:00+00:00", "actual_runway": "2026-07-11T09:06:00+00:00"}, "arrival": {"airport": "Sofia", "timezone": "Europe/Sofia", "iata": "SOF", "icao": "LBSF", "terminal": "2", "gate": null, "baggage": "2", "scheduled": "2026-07-11T10:05:00+00:00", "delay": 17, "estimated": "2026-07-11T10:00:00+00:00", "actual": null, "estimated_runway": null, "actual_runway": null}, "airline": {"name": "Aegean Airlines", "iata": "A3", "icao": "AEE"}, "flight": {"number": "980", "iata": "A3980", "icao": "AEE980", "codeshared": null}, "aircraft": {"registration": null, "iata": null, "icao": null, "icao24": "4692D9"}, "live": null}, {"flight_date": "2026-07-11", "flight_status": "active", "departure": {"airport": "Stuttgart Echterdingen", "timezone": "Europe/Berlin", "iata": "STR", "icao": "EDDS", "terminal": null, "gate": null, "delay": null, "scheduled": "2026-07-11T07:55:00+00:00", "estimated": "2026-07-11T07:55:00+00:00", "actual": "2026-07-11T07:59:00+00:00", "estimated_runway": "2026-07-11T07:59:00+00:00", "actual_runway": "2026-07-11T07:59:00+00:00"}, "arrival": {"airport": "Sofia", "timezone": "Europe/Sofia", "iata": "SOF", "icao": "LBSF", "terminal": "1", "gate": null, "baggage": "1", "scheduled": "2026-07-11T11:05:00+00:00", "delay": 5, "estimated": "2026-07-11T10:45:00+00:00", "actual": null, "estimated_runway": null, "actual_runway": null}, "airline": {"name": "Wizz Air", "iata": "W6", "icao": "WZZ"}, "flight": {"number": "4336", "iata": "W64336", "icao": "WZZ4336", "codeshared": null}, "aircraft": {"registration": null, "iata": null, "icao": null, "icao24": "471D67"}, "live": null}, {"flight_date": "2026-07-11", "flight_status": "active", "departure": {"airport": "Bergamo - Orio al Serio", "timezone": "Europe/Rome", "iata": "BGY", "icao": "LIME", "terminal": null, "gate": null, "delay": null, "scheduled": "2026-07-11T08:10:00+00:00", "estimated": "2026-07-11T08:10:00+00:00", "actual": null, "estimated_runway": null, "actual_runway": null}, "arrival": {"airport": "Sofia", "timezone": "Europe/Sofia", "iata": "SOF", "icao": "LBSF", "terminal": "1", "gate": null, "baggage": "2", "scheduled": "2026-07-11T11:10:00+00:00", "delay": null, "estimated": null, "actual": null, "estimated_runway": null, "actual_runway": null}, "airline": {"name": "Wizz Air", "iata": "W6", "icao": "WZZ"}, "flight": {"number": "4352", "iata": "W64352", "icao": "WZZ4352", "codeshared": null}, "aircraft": {"registration": null, "iata": null, "icao": null, "icao24": "4D2049"}, "live": null}, {"flight_date": "2026-07-11", "flight_status": "active", "departure": {"airport": "Antalya", "timezone": "Europe/Istanbul", "iata": "AYT", "icao": "LTAI", "terminal": "2", "gate": "514", "delay": null, "scheduled": "2026-07-11T09:15:00+00:00", "estimated": "2026-07-11T09:15:00+00:00", "actual": null, "estimated_runway": null, "actual_runway": null}, "arrival": {"airport": "Sofia", "timezone": "Europe/Sofia", "iata": "SOF", "icao": "LBSF", "terminal": "2", "gate": null, "baggage": "4", "scheduled": "2026-07-11T11:10:00+00:00", "delay": 20, "estimated": null, "actual": null, "estimated_runway": null, "actual_runway": null}, "airline": {"name": "Pegasus", "iata": "PC", "icao": "PGT"}, "flight": {"number": "5543", "iata": "PC5543", "icao": "PGT5543", "codeshared": null}, "aircraft": {"registration": null, "iata": null, "icao": null, "icao24": "4BB87A"}, "live": null}, {"flight_date": "2026-07-11", "flight_status": "scheduled", "departure": {"airport": "Prague Vaclav Havel Airport", "timezone": "Europe/Prague", "iata": "PRG", "icao": "LKPR", "terminal": "2", "gate": "200", "delay": null, "scheduled": "2026-07-11T08:45:00+00:00", "estimated": "2026-07-11T08:45:00+00:00", "actual": null, "estimated_runway": null, "actual_runway": null}, "arrival": {"airport": "Sofia", "timezone": "Europe/Sofia", "iata": "SOF", "icao": "LBSF", "terminal": "1", "gate": null, "baggage": "50", "scheduled": "2026-07-11T11:40:00+00:00", "delay": null, "estimated": null, "actual": null, "estimated_runway": null, "actual_runway": null}, "airline": {"name": "Wizz Air", "iata": "W6", "icao": "WZZ"}, "flight": {"number": "4450", "iata": "W64450", "icao": "WZZ4450", "codeshared": null}, "aircraft": {"registration": null, "iata": null, "icao": null, "icao24": "4D2425"}, "live": null}, {"flight_date": "2026-07-11", "flight_status": "active", "departure": {"airport": "Charleroi Brussels South", "timezone": "Europe/Brussels", "iata": "CRL", "icao": "EBCI", "terminal": null, "gate": "9", "delay": null, "scheduled": "2026-07-11T08:05:00+00:00", "estimated": "2026-07-11T08:05:00+00:00", "actual": "2026-07-11T08:15:00+00:00", "estimated_runway": "2026-07-11T08:15:00+00:00", "actual_runway": "2026-07-11T08:15:00+00:00"}, "arrival": {"airport": "Sofia", "timezone": "Europe/Sofia", "iata": "SOF", "icao": "LBSF", "terminal": "2", "gate": null, "baggage": null, "scheduled": "2026-07-11T11:40:00+00:00", "delay": 10, "estimated": "2026-07-11T11:25:00+00:00", "actual": null, "estimated_runway": null, "actual_runway": null}, "airline": {"name": "Ryanair", "iata": "FR", "icao": "RYR"}, "flight": {"number": "4962", "iata": "FR4962", "icao": "RYR4962", "codeshared": null}, "aircraft": {"registration": null, "iata": null, "icao": null, "icao24": "4CA56A"}, "live": null}, {"flight_date": "2026-07-11", "flight_status": "scheduled", "departure": {"airport": "Cote D'azur International Airport", "timezone": "Europe/Paris", "iata": "NCE", "icao": "LFMN", "terminal": "2", "gate": null, "delay": null, "scheduled": "2026-07-11T08:30:00+00:00", "estimated": "2026-07-11T08:30:00+00:00", "actual": null, "estimated_runway": null, "actual_runway": null}, "arrival": {"airport": "Sofia", "timezone": "Europe/Sofia", "iata": "SOF", "icao": "LBSF", "terminal": "1", "gate": null, "baggage": null, "scheduled": "2026-07-11T11:45:00+00:00", "delay": null, "estimated": null, "actual": null, "estimated_runway": null, "actual_runway": null}, "airline": {"name": "Wizz Air", "iata": "W6", "icao": "WZZ"}, "flight": {"number": "4416", "iata": "W64416", "icao": "WZZ4416", "codeshared": null}, "aircraft": {"registration": null, "iata": null, "icao": null, "icao24": "4D2491"}, "live": null}, {"flight_date": "2026-07-11", "flight_status": "active", "departure": {"airport": "Geneve-cointrin", "timezone": "Europe/Zurich", "iata": "GVA", "icao": "LSGG", "terminal": null, "gate": null, "delay": null, "scheduled": "2026-07-11T09:00:00+00:00", "estimated": "2026-07-11T09:00:00+00:00", "actual": null, "estimated_runway": null, "actual_runway": null}, "arrival": {"airport": "Sofia", "timezone": "Europe/Sofia", "iata": "SOF", "icao": "LBSF", "terminal": null, "gate": null, "baggage": null, "scheduled": "2026-07-11T12:02:00+00:00", "delay": 13, "estimated": null, "actual": null, "estimated_runway": null, "actual_runway": null}, "airline": {"name": "EGT Jet", "iata": null, "icao": "EGT"}, "flight": {"number": "336", "iata": null, "icao": "EGT336", "codeshared": null}, "aircraft": null, "live": null}, {"flight_date": "2026-07-11", "flight_status": "scheduled", "departure": {"airport": "Franz Josef Strauss", "timezone": "Europe/Berlin", "iata": "MUC", "icao": "EDDM", "terminal": "2", "gate": "K3", "delay": null, "scheduled": "2026-07-11T09:15:00+00:00", "estimated": "2026-07-11T09:15:00+00:00", "actual": null, "estimated_runway": null, "actual_runway": null}, "arrival": {"airport": "Sofia", "timezone": "Europe/Sofia", "iata": "SOF", "icao": "LBSF", "terminal": "2", "gate": null, "baggage": null, "scheduled": "2026-07-11T12:10:00+00:00", "delay": null, "estimated": null, "actual": null, "estimated_runway": null, "actual_runway": null}, "airline": {"name": "United Airlines", "iata": "UA", "icao": "UAL"}, "flight": {"number": "9246", "iata": "UA9246", "icao": "UAL9246", "codeshared": {"airline_name": "lufthansa", "airline_iata": "lh", "airline_icao": "dlh", "flight_number": "1702", "flight_iata": "lh1702", "flight_icao": "dlh1702"}}, "aircraft": {"registration": null, "iata": null, "icao": null, "icao24": "3C66A3"}, "live": null}, {"flight_date": "2026-07-11", "flight_status": "scheduled", "departure": {"airport": "Franz Josef Strauss", "timezone": "Europe/Berlin", "iata": "MUC", "icao": "EDDM", "terminal": "2", "gate": "K3", "delay": null, "scheduled": "2026-07-11T09:15:00+00:00", "estimated": "2026-07-11T09:15:00+00:00", "actual": null, "estimated_runway": null, "actual_runway": null}, "arrival": {"airport": "Sofia", "timezone": "Europe/Sofia", "iata": "SOF", "icao": "LBSF", "terminal": "2", "gate": null, "baggage": null, "scheduled": "2026-07-11T12:10:00+00:00", "delay": null, "estimated": null, "actual": null, "estimated_runway": null, "actual_runway": null}, "airline": {"name": "Singapore Airlines", "iata": "SQ", "icao": "SIA"}, "flight": {"number": "2168", "iata": "SQ2168", "icao": "SIA2168", "codeshared": {"airline_name": "lufthansa", "airline_iata": "lh", "airline_icao": "dlh", "flight_number": "1702", "flight_iata": "lh1702", "flight_icao": "dlh1702"}}, "aircraft": {"registration": null, "iata": null, "icao": null, "icao24": "3C66A3"}, "live": null}, {"flight_date": "2026-07-11", "flight_status": "scheduled", "departure": {"airport": "Franz Josef Strauss", "timezone": "Europe/Berlin", "iata": "MUC", "icao": "EDDM", "terminal": "2", "gate": "K3", "delay": null, "scheduled": "2026-07-11T09:15:00+00:00", "estimated": "2026-07-11T09:15:00+00:00", "actual": null, "estimated_runway": null, "actual_runway": null}, "arrival": {"airport": "Sofia", "timezone": "Europe/Sofia", "iata": "SOF", "icao": "LBSF", "terminal": "2", "gate": null, "baggage": null, "scheduled": "2026-07-11T12:10:00+00:00", "delay": null, "estimated": null, "actual": null, "estimated_runway": null, "actual_runway": null}, "airline": {"name": "All Nippon Airways", "iata": "NH", "icao": "ANA"}, "flight": {"number": "7890", "iata": "NH7890", "icao": "ANA7890", "codeshared": {"airline_name": "lufthansa", "airline_iata": "lh", "airline_icao": "dlh", "flight_number": "1702", "flight_iata": "lh1702", "flight_icao": "dlh1702"}}, "aircraft": {"registration": null, "iata": null, "icao": null, "icao24": "3C66A3"}, "live": null}, {"flight_date": "2026-07-11", "flight_status": "scheduled", "departure": {"airport": "Franz Josef Strauss", "timezone": "Europe/Berlin", "iata": "MUC", "icao": "EDDM", "terminal": "2", "gate": "K3", "delay": null, "scheduled": "2026-07-11T09:15:00+00:00", "estimated": "2026-07-11T09:15:00+00:00", "actual": null, "estimated_runway": null, "actual_runway": null}, "arrival": {"airport": "Sofia", "timezone": "Europe/Sofia", "iata": "SOF", "icao": "LBSF", "terminal": "2", "gate": null, "baggage": null, "scheduled": "2026-07-11T12:10:00+00:00", "delay": null, "estimated": null, "actual": null, "estimated_runway": null, "actual_runway": null}, "airline": {"name": "Swiss", "iata": "LX", "icao": "SWR"}, "flight": {"number": "3816", "iata": "LX3816", "icao": "SWR3816", "codeshared": {"airline_name": "lufthansa", "airline_iata": "lh", "airline_icao": "dlh", "flight_number": "1702", "flight_iata": "lh1702", "flight_icao": "dlh1702"}}, "aircraft": {"registration": null, "iata": null, "icao": null, "icao24": "3C66A3"}, "live": null}, {"flight_date": "2026-07-11", "flight_status": "scheduled", "departure": {"airport": "Franz Josef Strauss", "timezone": "Europe/Berlin", "iata": "MUC", "icao": "EDDM", "terminal": "2", "gate": "K3", "delay": null, "scheduled": "2026-07-11T09:15:00+00:00", "estimated": "2026-07-11T09:15:00+00:00", "actual": null, "estimated_runway": null, "actual_runway": null}, "arrival": {"airport": "Sofia", "timezone": "Europe/Sofia", "iata": "SOF", "icao": "LBSF", "terminal": "2", "gate": null, "baggage": null, "scheduled": "2026-07-11T12:10:00+00:00", "delay": null, "estimated": null, "actual": null, "estimated_runway": null, "actual_runway": null}, "airline": {"name": "Air Canada", "iata": "AC", "icao": "ACA"}, "flight": {"number": "9602", "iata": "AC9602", "icao": "ACA9602", "codeshared": {"airline_name": "lufthansa", "airline_iata": "lh", "airline_icao": "dlh", "flight_number": "1702", "flight_iata": "lh1702", "flight_icao": "dlh1702"}}, "aircraft": {"registration": null, "iata": null, "icao": null, "icao24": "3C66A3"}, "live": null}, {"flight_date": "2026-07-11", "flight_status": "active", "departure": {"airport": "Leonardo Da Vinci (Fiumicino)", "timezone": "Europe/Rome", "iata": "FCO", "icao": "LIRF", "terminal": "1", "gate": null, "delay": null, "scheduled": "2026-07-11T09:05:00+00:00", "estimated": "2026-07-11T09:05:00+00:00", "actual": null, "estimated_runway": null, "actual_runway": null}, "arrival": {"airport": "Sofia", "timezone": "Europe/Sofia", "iata": "SOF", "icao": "LBSF", "terminal": "2", "gate": null, "baggage": null, "scheduled": "2026-07-11T12:10:00+00:00", "delay": 11, "estimated": null, "actual": null, "estimated_runway": null, "actual_runway": null}, "airline": {"name": "Qatar Airways", "iata": "QR", "icao": "QTR"}, "flight": {"number": "5550", "iata": "QR5550", "icao": "QTR5550", "codeshared": {"airline_name": "bulgaria air", "airline_iata": "fb", "airline_icao": "lzb", "flight_number": "450", "flight_iata": "fb450", "flight_icao": "lzb450"}}, "aircraft": {"registration": null, "iata": null, "icao": null, "icao24": "452163"}, "live": null}, {"flight_date": "2026-07-11", "flight_status": "active", "departure": {"airport": "Leonardo Da Vinci (Fiumicino)", "timezone": "Europe/Rome", "iata": "FCO", "icao": "LIRF", "terminal": "1", "gate": null, "delay": null, "scheduled": "2026-07-11T09:05:00+00:00", "estimated": "2026-07-11T09:05:00+00:00", "actual": null, "estimated_runway": null, "actual_runway": null}, "arrival": {"airport": "Sofia", "timezone": "Europe/Sofia", "iata": "SOF", "icao": "LBSF", "terminal": "2", "gate": null, "baggage": null, "scheduled": "2026-07-11T12:10:00+00:00", "delay": 11, "estimated": null, "actual": null, "estimated_runway": null, "actual_runway": null}, "airline": {"name": "Alitalia", "iata": "AZ", "icao": "AZA"}, "flight": {"number": "7178", "iata": "AZ7178", "icao": "AZA7178", "codeshared": {"airline_name": "bulgaria air", "airline_iata": "fb", "airline_icao": "lzb", "flight_number": "450", "flight_iata": "fb450", "flight_icao": "lzb450"}}, "aircraft": {"registration": null, "iata": null, "icao": null, "icao24": "452163"}, "live": null}, {"flight_date": "2026-07-11", "flight_status": "scheduled", "departure": {"airport": "Franz Josef Strauss", "timezone": "Europe/Berlin", "iata": "MUC", "icao": "EDDM", "terminal": "2", "gate": "K3", "delay": null, "scheduled": "2026-07-11T09:15:00+00:00", "estimated": "2026-07-11T09:15:00+00:00", "actual": null, "estimated_runway": null, "actual_runway": null}, "arrival": {"airport": "Sofia", "timezone": "Europe/Sofia", "iata": "SOF", "icao": "LBSF", "terminal": "2", "gate": null, "baggage": null, "scheduled": "2026-07-11T12:10:00+00:00", "delay": null, "estimated": null, "actual": null, "estimated_runway": null, "actual_runway": null}, "airline": {"name": "Lufthansa", "iata": "LH", "icao": "DLH"}, "flight": {"number": "1702", "iata": "LH1702", "icao": "DLH1702", "codeshared": null}, "aircraft": {"registration": null, "iata": null, "icao": null, "icao24": "3C66A3"}, "live": null}, {"flight_date": "2026-07-11", "flight_status": "active", "departure": {"airport": "Leonardo Da Vinci (Fiumicino)", "timezone": "Europe/Rome", "iata": "FCO", "icao": "LIRF", "terminal": "1", "gate": null, "delay": null, "scheduled": "2026-07-11T09:05:00+00:00", "estimated": "2026-07-11T09:05:00+00:00", "actual": null, "estimated_runway": null, "actual_runway": null}, "arrival": {"airport": "Sofia", "timezone": "Europe/Sofia", "iata": "SOF", "icao": "LBSF", "terminal": "2", "gate": null, "baggage": null, "scheduled": "2026-07-11T12:10:00+00:00", "delay": 11, "estimated": null, "actual": null, "estimated_runway": null, "actual_runway": null}, "airline": {"name": "Bulgaria Air", "iata": "FB", "icao": "LZB"}, "flight": {"number": "450", "iata": "FB450", "icao": "LZB450", "codeshared": null}, "aircraft": {"registration": null, "iata": null, "icao": null, "icao24": "452163"}, "live": null}, {"flight_date": "2026-07-11", "flight_status": "active", "departure": {"airport": "Dortmund", "timezone": "Europe/Berlin", "iata": "DTM", "icao": "EDLW", "terminal": null, "gate": "5", "delay": null, "scheduled": "2026-07-11T08:45:00+00:00", "estimated": "2026-07-11T08:45:00+00:00", "actual": null, "estimated_runway": null, "actual_runway": null}, "arrival": {"airport": "Sofia", "timezone": "Europe/Sofia", "iata": "SOF", "icao": "LBSF", "terminal": "1", "gate": null, "baggage": null, "scheduled": "2026-07-11T12:15:00+00:00", "delay": null, "estimated": null, "actual": null, "estimated_runway": null, "actual_runway": null}, "airline": {"name": "Wizz Air", "iata": "W6", "icao": "WZZ"}, "flight": {"number": "4332", "iata": "W64332", "icao": "WZZ4332", "codeshared": null}, "aircraft": {"registration": null, "iata": null, "icao": null, "icao24": "471FAC"}, "live": null}, {"flight_date": "2026-07-11", "flight_status": "active", "departure": {"airport": "Stansted", "timezone": "Europe/London", "iata": "STN", "icao": "EGSS", "terminal": null, "gate": "36", "delay": null, "scheduled": "2026-07-11T07:25:00+00:00", "estimated": "2026-07-11T07:25:00+00:00", "actual": null, "estimated_runway": null, "actual_runway": null}, "arrival": {"airport": "Sofia", "timezone": "Europe/Sofia", "iata": "SOF", "icao": "LBSF", "terminal": "2", "gate": null, "baggage": null, "scheduled": "2026-07-11T12:25:00+00:00", "delay": 11, "estimated": null, "actual": null, "estimated_runway": null, "actual_runway": null}, "airline": {"name": "Ryanair", "iata": "FR", "icao": "RYR"}, "flight": {"number": "2690", "iata": "FR2690", "icao": "RYR2690", "codeshared": null}, "aircraft": {"registration": null, "iata": null, "icao": null, "icao24": "48C234"}, "live": null}, {"flight_date": "2026-07-11", "flight_status": "scheduled", "departure": {"airport": "Sabiha Gokcen", "timezone": "Europe/Istanbul", "iata": "SAW", "icao": "LTFJ", "terminal": null, "gate": "D1", "delay": null, "scheduled": "2026-07-11T11:10:00+00:00", "estimated": "2026-07-11T11:10:00+00:00", "actual": null, "estimated_runway": null, "actual_runway": null}, "arrival": {"airport": "Sofia", "timezone": "Europe/Sofia", "iata": "SOF", "icao": "LBSF", "terminal": "2", "gate": null, "baggage": null, "scheduled": "2026-07-11T12:30:00+00:00", "delay": null, "estimated": null, "actual": null, "estimated_runway": null, "actual_runway": null}, "airline": {"name": "Pegasus", "iata": "PC", "icao": "PGT"}, "flight": {"number": "271", "iata": "PC271", "icao": "PGT271", "codeshared": null}, "aircraft": {"registration": null, "iata": null, "icao": null, "icao24": "4BC886"}, "live": null}, {"flight_date": "2026-07-11", "flight_status": "scheduled", "departure": {"airport": "Vienna International", "timezone": "Europe/Vienna", "iata": "VIE", "icao": "LOWW", "terminal": "3", "gate": "F", "delay": null, "scheduled": "2026-07-11T10:25:00+00:00", "estimated": "2026-07-11T10:25:00+00:00", "actual": null, "estimated_runway": null, "actual_runway": null}, "arrival": {"airport": "Sofia", "timezone": "Europe/Sofia", "iata": "SOF", "icao": "LBSF", "terminal": "2", "gate": null, "baggage": null, "scheduled": "2026-07-11T12:55:00+00:00", "delay": null, "estimated": null, "actual": null, "estimated_runway": null, "actual_runway": null}, "airline": {"name": "All Nippon Airways", "iata": "NH", "icao": "ANA"}, "flight": {"number": "5635", "iata": "NH5635", "icao": "ANA5635", "codeshared": {"airline_name": "austrian airlines", "airline_iata": "os", "airline_icao": "aua", "flight_number": "771", "flight_iata": "os771", "flight_icao": "aua771"}}, "aircraft": {"registration": null, "iata": null, "icao": null, "icao24": "44082A"}, "live": null}, {"flight_date": "2026-07-11", "flight_status": "scheduled", "departure": {"airport": "Vienna International", "timezone": "Europe/Vienna", "iata": "VIE", "icao": "LOWW", "terminal": "3", "gate": "F", "delay": null, "scheduled": "2026-07-11T10:25:00+00:00", "estimated": "2026-07-11T10:25:00+00:00", "actual": null, "estimated_runway": null, "actual_runway": null}, "arrival": {"airport": "Sofia", "timezone": "Europe/Sofia", "iata": "SOF", "icao": "LBSF", "terminal": "2", "gate": null, "baggage": null, "scheduled": "2026-07-11T12:55:00+00:00", "delay": 9, "estimated": null, "actual": null, "estimated_runway": null, "actual_runway": null}, "airline": {"name": "Austrian Airlines", "iata": "OS", "icao": "AUA"}, "flight": {"number": "771", "iata": "OS771", "icao": "AUA771", "codeshared": null}, "aircraft": {"registration": null, "iata": null, "icao": null, "icao24": "44082A"}, "live": null}, {"flight_date": "2026-07-11", "flight_status": "scheduled", "departure": {"airport": "Vienna International", "timezone": "Europe/Vienna", "iata": "VIE", "icao": "LOWW", "terminal": "3", "gate": "F", "delay": null, "scheduled": "2026-07-11T10:25:00+00:00", "estimated": "2026-07-11T10:25:00+00:00", "actual": null, "estimated_runway": null, "actual_runway": null}, "arrival": {"airport": "Sofia", "timezone": "Europe/Sofia", "iata": "SOF", "icao": "LBSF", "terminal": "2", "gate": null, "baggage": null, "scheduled": "2026-07-11T12:55:00+00:00", "delay": 9, "estimated": null, "actual": null, "estimated_runway": null, "actual_runway": null}, "airline": {"name": "United Airlines", "iata": "UA", "icao": "UAL"}, "flight": {"number": "9832", "iata": "UA9832", "icao": "UAL9832", "codeshared": {"airline_name": "austrian airlines", "airline_iata": "os", "airline_icao": "aua", "flight_number": "771", "flight_iata": "os771", "flight_icao": "aua771"}}, "aircraft": {"registration": null, "iata": null, "icao": null, "icao24": "44082A"}, "live": null}, {"flight_date": "2026-07-11", "flight_status": "active", "departure": {"airport": "Zurich", "timezone": "Europe/Zurich", "iata": "ZRH", "icao": "LSZH", "terminal": "1", "gate": "A51", "delay": null, "scheduled": "2026-07-11T09:40:00+00:00", "estimated": "2026-07-11T09:40:00+00:00", "actual": null, "estimated_runway": null, "actual_runway": null}, "arrival": {"airport": "Sofia", "timezone": "Europe/Sofia", "iata": "SOF", "icao": "LBSF", "terminal": "2", "gate": null, "baggage": null, "scheduled": "2026-07-11T12:55:00+00:00", "delay": null, "estimated": null, "actual": null, "estimated_runway": null, "actual_runway": null}, "airline": {"name": "Helvetic Airways", "iata": "2L", "icao": "OAW"}, "flight": {"number": "1390", "iata": "2L1390", "icao": "OAW1390", "codeshared": null}, "aircraft": {"registration": null, "iata": null, "icao": null, "icao24": "4B0295"}, "live": null}, {"flight_date": "2026-07-11", "flight_status": "scheduled", "departure": {"airport": "Varna", "timezone": "Europe/Sofia", "iata": "VAR", "icao": "LBWN", "terminal": null, "gate": null, "delay": null, "scheduled": "2026-07-11T12:10:00+00:00", "estimated": "2026-07-11T12:10:00+00:00", "actual": null, "estimated_runway": null, "actual_runway": null}, "arrival": {"airport": "Sofia", "timezone": "Europe/Sofia", "iata": "SOF", "icao": "LBSF", "terminal": "2", "gate": null, "baggage": null, "scheduled": "2026-07-11T13:00:00+00:00", "delay": 10, "estimated": null, "actual": null, "estimated_runway": null, "actual_runway": null}, "airline": {"name": "Bulgaria Air", "iata": "FB", "icao": "LZB"}, "flight": {"number": "976", "iata": "FB976", "icao": "LZB976", "codeshared": null}, "aircraft": {"registration": null, "iata": null, "icao": null, "icao24": "452142"}, "live": null}, {"flight_date": "2026-07-11", "flight_status": "scheduled", "departure": {"airport": "Varna", "timezone": "Europe/Sofia", "iata": "VAR", "icao": "LBWN", "terminal": null, "gate": null, "delay": null, "scheduled": "2026-07-11T12:10:00+00:00", "estimated": "2026-07-11T12:10:00+00:00", "actual": null, "estimated_runway": null, "actual_runway": null}, "arrival": {"airport": "Sofia", "timezone": "Europe/Sofia", "iata": "SOF", "icao": "LBSF", "terminal": "2", "gate": null, "baggage": null, "scheduled": "2026-07-11T13:00:00+00:00", "delay": 10, "estimated": null, "actual": null, "estimated_runway": null, "actual_runway": null}, "airline": {"name": "Qatar Airways", "iata": "QR", "icao": "QTR"}, "flight": {"number": "5546", "iata": "QR5546", "icao": "QTR5546", "codeshared": {"airline_name": "bulgaria air", "airline_iata": "fb", "airline_icao": "lzb", "flight_number": "976", "flight_iata": "fb976", "flight_icao": "lzb976"}}, "aircraft": {"registration": null, "iata": null, "icao": null, "icao24": "452142"}, "live": null}, {"flight_date": "2026-07-11", "flight_status": "scheduled", "departure": {"airport": "Mandelieu", "timezone": "Europe/Paris", "iata": "CEQ", "icao": "LFMD", "terminal": null, "gate": null, "delay": null, "scheduled": "2026-07-11T10:15:00+00:00", "estimated": "2026-07-11T10:15:00+00:00", "actual": null, "estimated_runway": null, "actual_runway": null}, "arrival": {"airport": "Sofia", "timezone": "Europe/Sofia", "iata": "SOF", "icao": "LBSF", "terminal": null, "gate": null, "baggage": null, "scheduled": "2026-07-11T13:11:00+00:00", "delay": null, "estimated": null, "actual": null, "estimated_runway": null, "actual_runway": null}, "airline": {"name": "NetJets", "iata": "1I", "icao": "EJA"}, "flight": {"number": null, "iata": "1I", "icao": "EJA", "codeshared": null}, "aircraft": {"registration": null, "iata": null, "icao": null, "icao24": "490D02"}, "live": null}, {"flight_date": "2026-07-11", "flight_status": "scheduled", "departure": {"airport": "Frankfurt International Airport", "timezone": "Europe/Berlin", "iata": "FRA", "icao": "EDDF", "terminal": "1", "gate": "B10", "delay": null, "scheduled": "2026-07-11T10:05:00+00:00", "estimated": "2026-07-11T10:05:00+00:00", "actual": null, "estimated_runway": null, "actual_runway": null}, "arrival": {"airport": "Sofia", "timezone": "Europe/Sofia", "iata": "SOF", "icao": "LBSF", "terminal": "2", "gate": null, "baggage": null, "scheduled": "2026-07-11T13:15:00+00:00", "delay": null, "estimated": null, "actual": null, "estimated_runway": null, "actual_runway": null}, "airline": {"name": "United Airlines", "iata": "UA", "icao": "UAL"}, "flight": {"number": "9124", "iata": "UA9124", "icao": "UAL9124", "codeshared": {"airline_name": "lufthansa", "airline_iata": "lh", "airline_icao": "dlh", "flight_number": "1426", "flight_iata": "lh1426", "flight_icao": "dlh1426"}}, "aircraft": {"registration": null, "iata": null, "icao": null, "icao24": "3C6650"}, "live": null}, {"flight_date": "2026-07-11", "flight_status": "scheduled", "departure": {"airport": "Frankfurt International Airport", "timezone": "Europe/Berlin", "iata": "FRA", "icao": "EDDF", "terminal": "1", "gate": "B10", "delay": null, "scheduled": "2026-07-11T10:05:00+00:00", "estimated": "2026-07-11T10:05:00+00:00", "actual": null, "estimated_runway": null, "actual_runway": null}, "arrival": {"airport": "Sofia", "timezone": "Europe/Sofia", "iata": "SOF", "icao": "LBSF", "terminal": "2", "gate": null, "baggage": null, "scheduled": "2026-07-11T13:15:00+00:00", "delay": null, "estimated": null, "actual": null, "estimated_runway": null, "actual_runway": null}, "airline": {"name": "TAP Air Portugal", "iata": "TP", "icao": "TAP"}, "flight": {"number": "7540", "iata": "TP7540", "icao": "TAP7540", "codeshared": {"airline_name": "lufthansa", "airline_iata": "lh", "airline_icao": "dlh", "flight_number": "1426", "flight_iata": "lh1426", "flight_icao": "dlh1426"}}, "aircraft": {"registration": null, "iata": null, "icao": null, "icao24": "3C6650"}, "live": null}, {"flight_date": "2026-07-11", "flight_status": "scheduled", "departure": {"airport": "Frankfurt International Airport", "timezone": "Europe/Berlin", "iata": "FRA", "icao": "EDDF", "terminal": "1", "gate": "B10", "delay": null, "scheduled": "2026-07-11T10:05:00+00:00", "estimated": "2026-07-11T10:05:00+00:00", "actual": null, "estimated_runway": null, "actual_runway": null}, "arrival": {"airport": "Sofia", "timezone": "Europe/Sofia", "iata": "SOF", "icao": "LBSF", "terminal": "2", "gate": null, "baggage": null, "scheduled": "2026-07-11T13:15:00+00:00", "delay": null, "estimated": null, "actual": null, "estimated_runway": null, "actual_runway": null}, "airline": {"name": "Singapore Airlines", "iata": "SQ", "icao": "SIA"}, "flight": {"number": "2118", "iata": "SQ2118", "icao": "SIA2118", "codeshared": {"airline_name": "lufthansa", "airline_iata": "lh", "airline_icao": "dlh", "flight_number": "1426", "flight_iata": "lh1426", "flight_icao": "dlh1426"}}, "aircraft": {"registration": null, "iata": null, "icao": null, "icao24": "3C6650"}, "live": null}, {"flight_date": "2026-07-11", "flight_status": "scheduled", "departure": {"airport": "Frankfurt International Airport", "timezone": "Europe/Berlin", "iata": "FRA", "icao": "EDDF", "terminal": "1", "gate": "B10", "delay": null, "scheduled": "2026-07-11T10:05:00+00:00", "estimated": "2026-07-11T10:05:00+00:00", "actual": null, "estimated_runway": null, "actual_runway": null}, "arrival": {"airport": "Sofia", "timezone": "Europe/Sofia", "iata": "SOF", "icao": "LBSF", "terminal": "2", "gate": null, "baggage": null, "scheduled": "2026-07-11T13:15:00+00:00", "delay": null, "estimated": null, "actual": null, "estimated_runway": null, "actual_runway": null}, "airline": {"name": "All Nippon Airways", "iata": "NH", "icao": "ANA"}, "flight": {"number": "7886", "iata": "NH7886", "icao": "ANA7886", "codeshared": {"airline_name": "lufthansa", "airline_iata": "lh", "airline_icao": "dlh", "flight_number": "1426", "flight_iata": "lh1426", "flight_icao": "dlh1426"}}, "aircraft": {"registration": null, "iata": null, "icao": null, "icao24": "3C6650"}, "live": null}, {"flight_date": "2026-07-11", "flight_status": "scheduled", "departure": {"airport": "Frankfurt International Airport", "timezone": "Europe/Berlin", "iata": "FRA", "icao": "EDDF", "terminal": "1", "gate": "B10", "delay": null, "scheduled": "2026-07-11T10:05:00+00:00", "estimated": "2026-07-11T10:05:00+00:00", "actual": null, "estimated_runway": null, "actual_runway": null}, "arrival": {"airport": "Sofia", "timezone": "Europe/Sofia", "iata": "SOF", "icao": "LBSF", "terminal": "2", "gate": null, "baggage": null, "scheduled": "2026-07-11T13:15:00+00:00", "delay": null, "estimated": null, "actual": null, "estimated_runway": null, "actual_runway": null}, "airline": {"name": "Ethiopian Airlines", "iata": "ET", "icao": "ETH"}, "flight": {"number": "1599", "iata": "ET1599", "icao": "ETH1599", "codeshared": {"airline_name": "lufthansa", "airline_iata": "lh", "airline_icao": "dlh", "flight_number": "1426", "flight_iata": "lh1426", "flight_icao": "dlh1426"}}, "aircraft": {"registration": null, "iata": null, "icao": null, "icao24": "3C6650"}, "live": null}, {"flight_date": "2026-07-11", "flight_status": "scheduled", "departure": {"airport": "Frankfurt International Airport", "timezone": "Europe/Berlin", "iata": "FRA", "icao": "EDDF", "terminal": "1", "gate": "B10", "delay": null, "scheduled": "2026-07-11T10:05:00+00:00", "estimated": "2026-07-11T10:05:00+00:00", "actual": null, "estimated_runway": null, "actual_runway": null}, "arrival": {"airport": "Sofia", "timezone": "Europe/Sofia", "iata": "SOF", "icao": "LBSF", "terminal": "2", "gate": null, "baggage": null, "scheduled": "2026-07-11T13:15:00+00:00", "delay": null, "estimated": null, "actual": null, "estimated_runway": null, "actual_runway": null}, "airline": {"name": "Air Canada", "iata": "AC", "icao": "ACA"}, "flight": {"number": "9487", "iata": "AC9487", "icao": "ACA9487", "codeshared": {"airline_name": "lufthansa", "airline_iata": "lh", "airline_icao": "dlh", "flight_number": "1426", "flight_iata": "lh1426", "flight_icao": "dlh1426"}}, "aircraft": {"registration": null, "iata": null, "icao": null, "icao24": "3C6650"}, "live": null}, {"flight_date": "2026-07-11", "flight_status": "scheduled", "departure": {"airport": "Frankfurt International Airport", "timezone": "Europe/Berlin", "iata": "FRA", "icao": "EDDF", "terminal": "1", "gate": "B10", "delay": null, "scheduled": "2026-07-11T10:05:00+00:00", "estimated": "2026-07-11T10:05:00+00:00", "actual": null, "estimated_runway": null, "actual_runway": null}, "arrival": {"airport": "Sofia", "timezone": "Europe/Sofia", "iata": "SOF", "icao": "LBSF", "terminal": "2", "gate": null, "baggage": null, "scheduled": "2026-07-11T13:15:00+00:00", "delay": 12, "estimated": null, "actual": null, "estimated_runway": null, "actual_runway": null}, "airline": {"name": "Lufthansa", "iata": "LH", "icao": "DLH"}, "flight": {"number": "1426", "iata": "LH1426", "icao": "DLH1426", "codeshared": null}, "aircraft": {"registration": null, "iata": null, "icao": null, "icao24": "3C6650"}, "live": null}, {"flight_date": "2026-07-11", "flight_status": "active", "departure": {"airport": "El Prat De Llobregat", "timezone": "Europe/Madrid", "iata": "BCN", "icao": "LEBL", "terminal": "2", "gate": "U35", "delay": null, "scheduled": "2026-07-11T09:20:00+00:00", "estimated": "2026-07-11T09:20:00+00:00", "actual": null, "estimated_runway": null, "actual_runway": null}, "arrival": {"airport": "Sofia", "timezone": "Europe/Sofia", "iata": "SOF", "icao": "LBSF", "terminal": "2", "gate": null, "baggage": null, "scheduled": "2026-07-11T13:15:00+00:00", "delay": null, "estimated": null, "actual": null, "estimated_runway": null, "actual_runway": null}, "airline": {"name": "Ryanair", "iata": "FR", "icao": "RYR"}, "flight": {"number": "6300", "iata": "FR6300", "icao": "RYR6300", "codeshared": null}, "aircraft": {"registration": null, "iata": null, "icao": null, "icao24": "4CA7B3"}, "live": null}, {"flight_date": "2026-07-11", "flight_status": "scheduled", "departure": {"airport": "Kastrup", "timezone": "Europe/Copenhagen", "iata": "CPH", "icao": "EKCH", "terminal": "2", "gate": "F", "delay": null, "scheduled": "2026-07-11T09:45:00+00:00", "estimated": "2026-07-11T09:45:00+00:00", "actual": null, "estimated_runway": null, "actual_runway": null}, "arrival": {"airport": "Sofia", "timezone": "Europe/Sofia", "iata": "SOF", "icao": "LBSF", "terminal": "2", "gate": null, "baggage": null, "scheduled": "2026-07-11T13:25:00+00:00", "delay": null, "estimated": null, "actual": null, "estimated_runway": null, "actual_runway": null}, "airline": {"name": "Ryanair", "iata": "FR", "icao": "RYR"}, "flight": {"number": "3606", "iata": "FR3606", "icao": "RYR3606", "codeshared": null}, "aircraft": {"registration": null, "iata": null, "icao": null, "icao24": "48C121"}, "live": null}, {"flight_date": "2026-07-11", "flight_status": "scheduled", "departure": {"airport": "Santander", "timezone": "Europe/Madrid", "iata": "SDR", "icao": "LEXJ", "terminal": "N", "gate": "1", "delay": null, "scheduled": "2026-07-11T09:05:00+00:00", "estimated": "2026-07-11T09:05:00+00:00", "actual": null, "estimated_runway": null, "actual_runway": null}, "arrival": {"airport": "Sofia", "timezone": "Europe/Sofia", "iata": "SOF", "icao": "LBSF", "terminal": "1", "gate": null, "baggage": null, "scheduled": "2026-07-11T13:25:00+00:00", "delay": null, "estimated": null, "actual": null, "estimated_runway": null, "actual_runway": null}, "airline": {"name": "Wizz Air", "iata": "W6", "icao": "WZZ"}, "flight": {"number": "4420", "iata": "W64420", "icao": "WZZ4420", "codeshared": null}, "aircraft": {"registration": null, "iata": null, "icao": null, "icao24": "471F9A"}, "live": null}, {"flight_date": "2026-07-11", "flight_status": "scheduled", "departure": {"airport": "Luton Airport", "timezone": "Europe/London", "iata": "LTN", "icao": "EGGW", "terminal": null, "gate": "12", "delay": null, "scheduled": "2026-07-11T08:20:00+00:00", "estimated": "2026-07-11T08:20:00+00:00", "actual": null, "estimated_runway": null, "actual_runway": null}, "arrival": {"airport": "Sofia", "timezone": "Europe/Sofia", "iata": "SOF", "icao": "LBSF", "terminal": "1", "gate": null, "baggage": null, "scheduled": "2026-07-11T13:35:00+00:00", "delay": null, "estimated": null, "actual": null, "estimated_runway": null, "actual_runway": null}, "airline": {"name": "Wizz Air", "iata": "W6", "icao": "WZZ"}, "flight": {"number": "4302", "iata": "W64302", "icao": "WZZ4302", "codeshared": null}, "aircraft": {"registration": null, "iata": null, "icao": null, "icao24": "471DB9"}, "live": null}, {"flight_date": "2026-07-11", "flight_status": "scheduled", "departure": {"airport": "Tivat", "timezone": "Europe/Podgorica", "iata": "TIV", "icao": "LYTV", "terminal": null, "gate": null, "delay": null, "scheduled": "2026-07-11T11:30:00+00:00", "estimated": "2026-07-11T11:30:00+00:00", "actual": null, "estimated_runway": null, "actual_runway": null}, "arrival": {"airport": "Sofia", "timezone": "Europe/Sofia", "iata": "SOF", "icao": "LBSF", "terminal": null, "gate": null, "baggage": null, "scheduled": "2026-07-11T13:38:00+00:00", "delay": 10, "estimated": null, "actual": null, "estimated_runway": null, "actual_runway": null}, "airline": {"name": "Aviostart", "iata": null, "icao": "VSR"}, "flight": {"number": "805", "iata": null, "icao": "VSR805", "codeshared": null}, "aircraft": {"registration": null, "iata": null, "icao": null, "icao24": "452026"}, "live": null}, {"flight_date": "2026-07-11", "flight_status": "active", "departure": {"airport": "Dublin International", "timezone": "Europe/Dublin", "iata": "DUB", "icao": "EIDW", "terminal": "1", "gate": "109", "delay": null, "scheduled": "2026-07-11T08:00:00+00:00", "estimated": "2026-07-11T08:00:00+00:00", "actual": null, "estimated_runway": null, "actual_runway": null}, "arrival": {"airport": "Sofia", "timezone": "Europe/Sofia", "iata": "SOF", "icao": "LBSF", "terminal": "2", "gate": null, "baggage": null, "scheduled": "2026-07-11T13:40:00+00:00", "delay": null, "estimated": null, "actual": null, "estimated_runway": null, "actual_runway": null}, "airline": {"name": "Ryanair", "iata": "FR", "icao": "RYR"}, "flight": {"number": "5203", "iata": "FR5203", "icao": "RYR5203", "codeshared": null}, "aircraft": {"registration": null, "iata": null, "icao": null, "icao24": "48C228"}, "live": null}, {"flight_date": "2026-07-11", "flight_status": "scheduled", "departure": {"airport": "Frederic Chopin", "timezone": "Europe/Warsaw", "iata": "WAW", "icao": "EPWA", "terminal": null, "gate": null, "delay": null, "scheduled": "2026-07-11T10:50:00+00:00", "estimated": "2026-07-11T10:50:00+00:00", "actual": null, "estimated_runway": null, "actual_runway": null}, "arrival": {"airport": "Sofia", "timezone": "Europe/Sofia", "iata": "SOF", "icao": "LBSF", "terminal": "2", "gate": null, "baggage": null, "scheduled": "2026-07-11T13:55:00+00:00", "delay": 15, "estimated": null, "actual": null, "estimated_runway": null, "actual_runway": null}, "airline": {"name": "LOT", "iata": "LO", "icao": "LOT"}, "flight": {"number": "631", "iata": "LO631", "icao": "LOT631", "codeshared": null}, "aircraft": {"registration": null, "iata": null, "icao": null, "icao24": "48AD0D"}, "live": null}, {"flight_date": "2026-07-11", "flight_status": "scheduled", "departure": {"airport": "Frederic Chopin", "timezone": "Europe/Warsaw", "iata": "WAW", "icao": "EPWA", "terminal": null, "gate": null, "delay": null, "scheduled": "2026-07-11T10:50:00+00:00", "estimated": "2026-07-11T10:50:00+00:00", "actual": null, "estimated_runway": null, "actual_runway": null}, "arrival": {"airport": "Sofia", "timezone": "Europe/Sofia", "iata": "SOF", "icao": "LBSF", "terminal": "2", "gate": null, "baggage": null, "scheduled": "2026-07-11T13:55:00+00:00", "delay": 15, "estimated": null, "actual": null, "estimated_runway": null, "actual_runway": null}, "airline": {"name": "SAS", "iata": "SK", "icao": "SAS"}, "flight": {"number": "8134", "iata": "SK8134", "icao": "SAS8134", "codeshared": {"airline_name": "lot", "airline_iata": "lo", "airline_icao": "lot", "flight_number": "631", "flight_iata": "lo631", "flight_icao": "lot631"}}, "aircraft": {"registration": null, "iata": null, "icao": null, "icao24": "48AD0D"}, "live": null}, {"flight_date": "2026-07-11", "flight_status": "scheduled", "departure": {"airport": "Schiphol", "timezone": "Europe/Amsterdam", "iata": "AMS", "icao": "EHAM", "terminal": "3", "gate": "C24", "delay": null, "scheduled": "2026-07-11T10:15:00+00:00", "estimated": "2026-07-11T10:15:00+00:00", "actual": null, "estimated_runway": null, "actual_runway": null}, "arrival": {"airport": "Sofia", "timezone": "Europe/Sofia", "iata": "SOF", "icao": "LBSF", "terminal": "2", "gate": null, "baggage": null, "scheduled": "2026-07-11T14:00:00+00:00", "delay": null, "estimated": null, "actual": null, "estimated_runway": null, "actual_runway": null}, "airline": {"name": "airBaltic", "iata": "BT", "icao": "BTI"}, "flight": {"number": "5105", "iata": "BT5105", "icao": "BTI5105", "codeshared": {"airline_name": "bulgaria air", "airline_iata": "fb", "airline_icao": "lzb", "flight_number": "462", "flight_iata": "fb462", "flight_icao": "lzb462"}}, "aircraft": {"registration": null, "iata": null, "icao": null, "icao24": "452122"}, "live": null}, {"flight_date": "2026-07-11", "flight_status": "scheduled", "departure": {"airport": "Schiphol", "timezone": "Europe/Amsterdam", "iata": "AMS", "icao": "EHAM", "terminal": "3", "gate": "C24", "delay": null, "scheduled": "2026-07-11T10:15:00+00:00", "estimated": "2026-07-11T10:15:00+00:00", "actual": null, "estimated_runway": null, "actual_runway": null}, "arrival": {"airport": "Sofia", "timezone": "Europe/Sofia", "iata": "SOF", "icao": "LBSF", "terminal": "2", "gate": null, "baggage": null, "scheduled": "2026-07-11T14:00:00+00:00", "delay": null, "estimated": null, "actual": null, "estimated_runway": null, "actual_runway": null}, "airline": {"name": "KLM", "iata": "KL", "icao": "KLM"}, "flight": {"number": "3077", "iata": "KL3077", "icao": "KLM3077", "codeshared": {"airline_name": "bulgaria air", "airline_iata": "fb", "airline_icao": "lzb", "flight_number": "462", "flight_iata": "fb462", "flight_icao": "lzb462"}}, "aircraft": {"registration": null, "iata": null, "icao": null, "icao24": "452122"}, "live": null}, {"flight_date": "2026-07-11", "flight_status": "scheduled", "departure": {"airport": "Charles De Gaulle", "timezone": "Europe/Paris", "iata": "CDG", "icao": "LFPG", "terminal": "1", "gate": null, "delay": null, "scheduled": "2026-07-11T10:15:00+00:00", "estimated": "2026-07-11T10:15:00+00:00", "actual": null, "estimated_runway": null, "actual_runway": null}, "arrival": {"airport": "Sofia", "timezone": "Europe/Sofia", "iata": "SOF", "icao": "LBSF", "terminal": "2", "gate": null, "baggage": null, "scheduled": "2026-07-11T14:00:00+00:00", "delay": null, "estimated": null, "actual": null, "estimated_runway": null, "actual_runway": null}, "airline": {"name": "Air France", "iata": "AF", "icao": "AFR"}, "flight": {"number": "5470", "iata": "AF5470", "icao": "AFR5470", "codeshared": {"airline_name": "bulgaria air", "airline_iata": "fb", "airline_icao": "lzb", "flight_number": "432", "flight_iata": "fb432", "flight_icao": "lzb432"}}, "aircraft": {"registration": null, "iata": null, "icao": null, "icao24": "452164"}, "live": null}, {"flight_date": "2026-07-11", "flight_status": "scheduled", "departure": {"airport": "Charles De Gaulle", "timezone": "Europe/Paris", "iata": "CDG", "icao": "LFPG", "terminal": "1", "gate": null, "delay": null, "scheduled": "2026-07-11T10:15:00+00:00", "estimated": "2026-07-11T10:15:00+00:00", "actual": null, "estimated_runway": null, "actual_runway": null}, "arrival": {"airport": "Sofia", "timezone": "Europe/Sofia", "iata": "SOF", "icao": "LBSF", "terminal": "2", "gate": null, "baggage": null, "scheduled": "2026-07-11T14:00:00+00:00", "delay": 16, "estimated": null, "actual": null, "estimated_runway": null, "actual_runway": null}, "airline": {"name": "Bulgaria Air", "iata": "FB", "icao": "LZB"}, "flight": {"number": "432", "iata": "FB432", "icao": "LZB432", "codeshared": null}, "aircraft": {"registration": null, "iata": null, "icao": null, "icao24": "452164"}, "live": null}, {"flight_date": "2026-07-11", "flight_status": "scheduled", "departure": {"airport": "Schiphol", "timezone": "Europe/Amsterdam", "iata": "AMS", "icao": "EHAM", "terminal": "3", "gate": "C24", "delay": null, "scheduled": "2026-07-11T10:15:00+00:00", "estimated": "2026-07-11T10:15:00+00:00", "actual": null, "estimated_runway": null, "actual_runway": null}, "arrival": {"airport": "Sofia", "timezone": "Europe/Sofia", "iata": "SOF", "icao": "LBSF", "terminal": "2", "gate": null, "baggage": null, "scheduled": "2026-07-11T14:00:00+00:00", "delay": null, "estimated": null, "actual": null, "estimated_runway": null, "actual_runway": null}, "airline": {"name": "Bulgaria Air", "iata": "FB", "icao": "LZB"}, "flight": {"number": "462", "iata": "FB462", "icao": "LZB462", "codeshared": null}, "aircraft": {"registration": null, "iata": null, "icao": null, "icao24": "452122"}, "live": null}, {"flight_date": "2026-07-11", "flight_status": "scheduled", "departure": {"airport": "Heathrow", "timezone": "Europe/London", "iata": "LHR", "icao": "EGLL", "terminal": "4", "gate": "D", "delay": null, "scheduled": "2026-07-11T08:55:00+00:00", "estimated": "2026-07-11T08:55:00+00:00", "actual": null, "estimated_runway": null, "actual_runway": null}, "arrival": {"airport": "Sofia", "timezone": "Europe/Sofia", "iata": "SOF", "icao": "LBSF", "terminal": "2", "gate": null, "baggage": null, "scheduled": "2026-07-11T14:05:00+00:00", "delay": null, "estimated": null, "actual": null, "estimated_runway": null, "actual_runway": null}, "airline": {"name": "Bulgaria Air", "iata": "FB", "icao": "LZB"}, "flight": {"number": "852", "iata": "FB852", "icao": "LZB852", "codeshared": null}, "aircraft": {"registration": null, "iata": null, "icao": null, "icao24": "45218E"}, "live": null}, {"flight_date": "2026-07-11", "flight_status": "scheduled", "departure": {"airport": "Riga International", "timezone": "Europe/Riga", "iata": "RIX", "icao": "EVRA", "terminal": null, "gate": null, "delay": null, "scheduled": "2026-07-11T11:40:00+00:00", "estimated": "2026-07-11T11:40:00+00:00", "actual": null, "estimated_runway": null, "actual_runway": null}, "arrival": {"airport": "Sofia", "timezone": "Europe/Sofia", "iata": "SOF", "icao": "LBSF", "terminal": "2", "gate": null, "baggage": null, "scheduled": "2026-07-11T14:15:00+00:00", "delay": null, "estimated": null, "actual": null, "estimated_runway": null, "actual_runway": null}, "airline": {"name": "airBaltic", "iata": "BT", "icao": "BTI"}, "flight": {"number": "467", "iata": "BT467", "icao": "BTI467", "codeshared": null}, "aircraft": {"registration": null, "iata": null, "icao": null, "icao24": "502CCD"}, "live": null}, {"flight_date": "2026-07-11", "flight_status": "scheduled", "departure": {"airport": "Riga International", "timezone": "Europe/Riga", "iata": "RIX", "icao": "EVRA", "terminal": null, "gate": null, "delay": null, "scheduled": "2026-07-11T11:40:00+00:00", "estimated": "2026-07-11T11:40:00+00:00", "actual": null, "estimated_runway": null, "actual_runway": null}, "arrival": {"airport": "Sofia", "timezone": "Europe/Sofia", "iata": "SOF", "icao": "LBSF", "terminal": "2", "gate": null, "baggage": null, "scheduled": "2026-07-11T14:15:00+00:00", "delay": null, "estimated": null, "actual": null, "estimated_runway": null, "actual_runway": null}, "airline": {"name": "AirSERBIA", "iata": "JU", "icao": "ASL"}, "flight": {"number": "7959", "iata": "JU7959", "icao": "ASL7959", "codeshared": {"airline_name": "airbaltic", "airline_iata": "bt", "airline_icao": "bti", "flight_number": "467", "flight_iata": "bt467", "flight_icao": "bti467"}}, "aircraft": {"registration": null, "iata": null, "icao": null, "icao24": "502CCD"}, "live": null}, {"flight_date": "2026-07-11", "flight_status": "scheduled", "departure": {"airport": "Riga International", "timezone": "Europe/Riga", "iata": "RIX", "icao": "EVRA", "terminal": null, "gate": null, "delay": null, "scheduled": "2026-07-11T11:40:00+00:00", "estimated": "2026-07-11T11:40:00+00:00", "actual": null, "estimated_runway": null, "actual_runway": null}, "arrival": {"airport": "Sofia", "timezone": "Europe/Sofia", "iata": "SOF", "icao": "LBSF", "terminal": "2", "gate": null, "baggage": null, "scheduled": "2026-07-11T14:15:00+00:00", "delay": null, "estimated": null, "actual": null, "estimated_runway": null, "actual_runway": null}, "airline": {"name": "Bulgaria Air", "iata": "FB", "icao": "LZB"}, "flight": {"number": "1452", "iata": "FB1452", "icao": "LZB1452", "codeshared": {"airline_name": "airbaltic", "airline_iata": "bt", "airline_icao": "bti", "flight_number": "467", "flight_iata": "bt467", "flight_icao": "bti467"}}, "aircraft": {"registration": null, "iata": null, "icao": null, "icao24": "502CCD"}, "live": null}, {"flight_date": "2026-07-11", "flight_status": "scheduled", "departure": {"airport": "Modlin", "timezone": "Europe/Warsaw", "iata": "WMI", "icao": "EPMO", "terminal": null, "gate": null, "delay": null, "scheduled": "2026-07-11T11:50:00+00:00", "estimated": "2026-07-11T11:50:00+00:00", "actual": null, "estimated_runway": null, "actual_runway": null}, "arrival": {"airport": "Sofia", "timezone": "Europe/Sofia", "iata": "SOF", "icao": "LBSF", "terminal": "2", "gate": null, "baggage": null, "scheduled": "2026-07-11T14:45:00+00:00", "delay": null, "estimated": null, "actual": null, "estimated_runway": null, "actual_runway": null}, "airline": {"name": "Ryanair", "iata": "FR", "icao": "RYR"}, "flight": {"number": "4035", "iata": "FR4035", "icao": "RYR4035", "codeshared": null}, "aircraft": {"registration": null, "iata": null, "icao": null, "icao24": "48C22B"}, "live": null}, {"flight_date": "2026-07-11", "flight_status": "scheduled", "departure": {"airport": "Istanbul Airport", "timezone": "Europe/Istanbul", "iata": "IST", "icao": "LTFM", "terminal": null, "gate": "B9A", "delay": null, "scheduled": "2026-07-11T13:45:00+00:00", "estimated": "2026-07-11T13:45:00+00:00", "actual": null, "estimated_runway": null, "actual_runway": null}, "arrival": {"airport": "Sofia", "timezone": "Europe/Sofia", "iata": "SOF", "icao": "LBSF", "terminal": "2", "gate": null, "baggage": null, "scheduled": "2026-07-11T15:00:00+00:00", "delay": null, "estimated": null, "actual": null, "estimated_runway": null, "actual_runway": null}, "airline": {"name": "Turkish Airlines", "iata": "TK", "icao": "THY"}, "flight": {"number": "1031", "iata": "TK1031", "icao": "THY1031", "codeshared": null}, "aircraft": {"registration": null, "iata": null, "icao": null, "icao24": "4BA91A"}, "live": null}, {"flight_date": "2026-07-11", "flight_status": "scheduled", "departure": {"airport": "Istanbul Airport", "timezone": "Europe/Istanbul", "iata": "IST", "icao": "LTFM", "terminal": null, "gate": "B9A", "delay": null, "scheduled": "2026-07-11T13:45:00+00:00", "estimated": "2026-07-11T13:45:00+00:00", "actual": null, "estimated_runway": null, "actual_runway": null}, "arrival": {"airport": "Sofia", "timezone": "Europe/Sofia", "iata": "SOF", "icao": "LBSF", "terminal": "2", "gate": null, "baggage": null, "scheduled": "2026-07-11T15:00:00+00:00", "delay": null, "estimated": null, "actual": null, "estimated_runway": null, "actual_runway": null}, "airline": {"name": "Singapore Airlines", "iata": "SQ", "icao": "SIA"}, "flight": {"number": "6219", "iata": "SQ6219", "icao": "SIA6219", "codeshared": {"airline_name": "turkish airlines", "airline_iata": "tk", "airline_icao": "thy", "flight_number": "1031", "flight_iata": "tk1031", "flight_icao": "thy1031"}}, "aircraft": {"registration": null, "iata": null, "icao": null, "icao24": "4BA91A"}, "live": null}, {"flight_date": "2026-07-11", "flight_status": "scheduled", "departure": {"airport": "Istanbul Airport", "timezone": "Europe/Istanbul", "iata": "IST", "icao": "LTFM", "terminal": null, "gate": "B9A", "delay": null, "scheduled": "2026-07-11T13:45:00+00:00", "estimated": "2026-07-11T13:45:00+00:00", "actual": null, "estimated_runway": null, "actual_runway": null}, "arrival": {"airport": "Sofia", "timezone": "Europe/Sofia", "iata": "SOF", "icao": "LBSF", "terminal": "2", "gate": null, "baggage": null, "scheduled": "2026-07-11T15:00:00+00:00", "delay": null, "estimated": null, "actual": null, "estimated_runway": null, "actual_runway": null}, "airline": {"name": "IndiGo", "iata": "6E", "icao": "IGO"}, "flight": {"number": "4119", "iata": "6E4119", "icao": "IGO4119", "codeshared": {"airline_name": "turkish airlines", "airline_iata": "tk", "airline_icao": "thy", "flight_number": "1031", "flight_iata": "tk1031", "flight_icao": "thy1031"}}, "aircraft": {"registration": null, "iata": null, "icao": null, "icao24": "4BA91A"}, "live": null}, {"flight_date": "2026-07-11", "flight_status": "scheduled", "departure": {"airport": "Memmingen-Allgäu", "timezone": "Europe/Berlin", "iata": "FMM", "icao": "EDJA", "terminal": null, "gate": null, "delay": null, "scheduled": "2026-07-11T12:15:00+00:00", "estimated": "2026-07-11T12:15:00+00:00", "actual": null, "estimated_runway": null, "actual_runway": null}, "arrival": {"airport": "Sofia", "timezone": "Europe/Sofia", "iata": "SOF", "icao": "LBSF", "terminal": "2", "gate": null, "baggage": null, "scheduled": "2026-07-11T15:15:00+00:00", "delay": null, "estimated": null, "actual": null, "estimated_runway": null, "actual_runway": null}, "airline": {"name": "Ryanair", "iata": "FR", "icao": "RYR"}, "flight": {"number": "6002", "iata": "FR6002", "icao": "RYR6002", "codeshared": null}, "aircraft": {"registration": null, "iata": null, "icao": null, "icao24": "48C138"}, "live": null}, {"flight_date": "2026-07-11", "flight_status": "scheduled", "departure": {"airport": "Vienna International", "timezone": "Europe/Vienna", "iata": "VIE", "icao": "LOWW", "terminal": "3", "gate": "F", "delay": null, "scheduled": "2026-07-11T12:50:00+00:00", "estimated": "2026-07-11T12:50:00+00:00", "actual": null, "estimated_runway": null, "actual_runway": null}, "arrival": {"airport": "Sofia", "timezone": "Europe/Sofia", "iata": "SOF", "icao": "LBSF", "terminal": "2", "gate": null, "baggage": null, "scheduled": "2026-07-11T15:20:00+00:00", "delay": 5, "estimated": null, "actual": null, "estimated_runway": null, "actual_runway": null}, "airline": {"name": "Austrian Airlines", "iata": "OS", "icao": "AUA"}, "flight": {"number": "773", "iata": "OS773", "icao": "AUA773", "codeshared": null}, "aircraft": {"registration": null, "iata": null, "icao": null, "icao24": "440821"}, "live": null}, {"flight_date": "2026-07-11", "flight_status": "scheduled", "departure": {"airport": "Belgrade Nikola Tesla", "timezone": "Europe/Belgrade", "iata": "BEG", "icao": "LYBE", "terminal": "2", "gate": null, "delay": null, "scheduled": "2026-07-11T13:15:00+00:00", "estimated": "2026-07-11T13:15:00+00:00", "actual": null, "estimated_runway": null, "actual_runway": null}, "arrival": {"airport": "Sofia", "timezone": "Europe/Sofia", "iata": "SOF", "icao": "LBSF", "terminal": "2", "gate": null, "baggage": null, "scheduled": "2026-07-11T15:30:00+00:00", "delay": null, "estimated": null, "actual": null, "estimated_runway": null, "actual_runway": null}, "airline": {"name": "Bulgaria Air", "iata": "FB", "icao": "LZB"}, "flight": {"number": "112", "iata": "FB112", "icao": "LZB112", "codeshared": null}, "aircraft": {"registration": null, "iata": null, "icao": null, "icao24": "451D8C"}, "live": null}, {"flight_date": "2026-07-11", "flight_status": "scheduled", "departure": {"airport": "Belgrade Nikola Tesla", "timezone": "Europe/Belgrade", "iata": "BEG", "icao": "LYBE", "terminal": "2", "gate": null, "delay": null, "scheduled": "2026-07-11T13:15:00+00:00", "estimated": "2026-07-11T13:15:00+00:00", "actual": null, "estimated_runway": null, "actual_runway": null}, "arrival": {"airport": "Sofia", "timezone": "Europe/Sofia", "iata": "SOF", "icao": "LBSF", "terminal": "2", "gate": null, "baggage": null, "scheduled": "2026-07-11T15:30:00+00:00", "delay": null, "estimated": null, "actual": null, "estimated_runway": null, "actual_runway": null}, "airline": {"name": "Bulgaria Air", "iata": "FB", "icao": "LZB"}, "flight": {"number": "1802", "iata": "FB1802", "icao": "LZB1802", "codeshared": {"airline_name": "bulgaria air", "airline_iata": "fb", "airline_icao": "lzb", "flight_number": "112", "flight_iata": "fb112", "flight_icao": "lzb112"}}, "aircraft": {"registration": null, "iata": null, "icao": null, "icao24": "451D8C"}, "live": null}, {"flight_date": "2026-07-11", "flight_status": "scheduled", "departure": {"airport": "Belgrade Nikola Tesla", "timezone": "Europe/Belgrade", "iata": "BEG", "icao": "LYBE", "terminal": "2", "gate": null, "delay": null, "scheduled": "2026-07-11T13:15:00+00:00", "estimated": "2026-07-11T13:15:00+00:00", "actual": null, "estimated_runway": null, "actual_runway": null}, "arrival": {"airport": "Sofia", "timezone": "Europe/Sofia", "iata": "SOF", "icao": "LBSF", "terminal": "2", "gate": null, "baggage": null, "scheduled": "2026-07-11T15:30:00+00:00", "delay": null, "estimated": null, "actual": null, "estimated_runway": null, "actual_runway": null}, "airline": {"name": "Etihad Airways", "iata": "EY", "icao": "ETD"}, "flight": {"number": "7918", "iata": "EY7918", "icao": "ETD7918", "codeshared": {"airline_name": "bulgaria air", "airline_iata": "fb", "airline_icao": "lzb", "flight_number": "112", "flight_iata": "fb112", "flight_icao": "lzb112"}}, "aircraft": {"registration": null, "iata": null, "icao": null, "icao24": "451D8C"}, "live": null}, {"flight_date": "2026-07-11", "flight_status": "scheduled", "departure": {"airport": "Belgrade Nikola Tesla", "timezone": "Europe/Belgrade", "iata": "BEG", "icao": "LYBE", "terminal": "2", "gate": null, "delay": null, "scheduled": "2026-07-11T13:15:00+00:00", "estimated": "2026-07-11T13:15:00+00:00", "actual": null, "estimated_runway": null, "actual_runway": null}, "arrival": {"airport": "Sofia", "timezone": "Europe/Sofia", "iata": "SOF", "icao": "LBSF", "terminal": "2", "gate": null, "baggage": null, "scheduled": "2026-07-11T15:30:00+00:00", "delay": null, "estimated": null, "actual": null, "estimated_runway": null, "actual_runway": null}, "airline": {"name": "JetBlue", "iata": "B6", "icao": "JBU"}, "flight": {"number": "6407", "iata": "B66407", "icao": "JBU6407", "codeshared": {"airline_name": "bulgaria air", "airline_iata": "fb", "airline_icao": "lzb", "flight_number": "112", "flight_iata": "fb112", "flight_icao": "lzb112"}}, "aircraft": {"registration": null, "iata": null, "icao": null, "icao24": "451D8C"}, "live": null}, {"flight_date": "2026-07-11", "flight_status": "scheduled", "departure": {"airport": "Belgrade Nikola Tesla", "timezone": "Europe/Belgrade", "iata": "BEG", "icao": "LYBE", "terminal": "2", "gate": null, "delay": null, "scheduled": "2026-07-11T13:15:00+00:00", "estimated": "2026-07-11T13:15:00+00:00", "actual": null, "estimated_runway": null, "actual_runway": null}, "arrival": {"airport": "Sofia", "timezone": "Europe/Sofia", "iata": "SOF", "icao": "LBSF", "terminal": "2", "gate": null, "baggage": null, "scheduled": "2026-07-11T15:30:00+00:00", "delay": null, "estimated": null, "actual": null, "estimated_runway": null, "actual_runway": null}, "airline": {"name": "Air France", "iata": "AF", "icao": "AFR"}, "flight": {"number": "3832", "iata": "AF3832", "icao": "AFR3832", "codeshared": {"airline_name": "bulgaria air", "airline_iata": "fb", "airline_icao": "lzb", "flight_number": "112", "flight_iata": "fb112", "flight_icao": "lzb112"}}, "aircraft": {"registration": null, "iata": null, "icao": null, "icao24": "451D8C"}, "live": null}, {"flight_date": "2026-07-11", "flight_status": "scheduled", "departure": {"airport": "Milas", "timezone": "Europe/Istanbul", "iata": "BJV", "icao": "LTFE", "terminal": "D", "gate": null, "delay": null, "scheduled": "2026-07-11T14:05:00+00:00", "estimated": "2026-07-11T14:05:00+00:00", "actual": null, "estimated_runway": null, "actual_runway": null}, "arrival": {"airport": "Sofia", "timezone": "Europe/Sofia", "iata": "SOF", "icao": "LBSF", "terminal": "2", "gate": null, "baggage": null, "scheduled": "2026-07-11T15:30:00+00:00", "delay": 10, "estimated": null, "actual": null, "estimated_runway": null, "actual_runway": null}, "airline": {"name": "Bulgaria Air", "iata": "FB", "icao": "LZB"}, "flight": {"number": "8794", "iata": "FB8794", "icao": "LZB8794", "codeshared": null}, "aircraft": {"registration": null, "iata": null, "icao": null, "icao24": "4520CF"}, "live": null}, {"flight_date": "2026-07-11", "flight_status": "scheduled", "departure": {"airport": "Punta Raisi", "timezone": "Europe/Rome", "iata": "PMO", "icao": "LICJ", "terminal": null, "gate": "A19", "delay": null, "scheduled": "2026-07-11T12:55:00+00:00", "estimated": "2026-07-11T12:55:00+00:00", "actual": null, "estimated_runway": null, "actual_runway": null}, "arrival": {"airport": "Sofia", "timezone": "Europe/Sofia", "iata": "SOF", "icao": "LBSF", "terminal": "1", "gate": null, "baggage": null, "scheduled": "2026-07-11T15:45:00+00:00", "delay": null, "estimated": null, "actual": null, "estimated_runway": null, "actual_runway": null}, "airline": {"name": "Wizz Air", "iata": "W6", "icao": "WZZ"}, "flight": {"number": "4314", "iata": "W64314", "icao": "WZZ4314", "codeshared": null}, "aircraft": {"registration": null, "iata": null, "icao": null, "icao24": "4D2424"}, "live": null}, {"flight_date": "2026-07-11", "flight_status": "scheduled", "departure": {"airport": "Miramare", "timezone": "Europe/Rome", "iata": "RMI", "icao": "LIPR", "terminal": null, "gate": null, "delay": null, "scheduled": "2026-07-11T13:10:00+00:00", "estimated": "2026-07-11T13:10:00+00:00", "actual": null, "estimated_runway": null, "actual_runway": null}, "arrival": {"airport": "Sofia", "timezone": "Europe/Sofia", "iata": "SOF", "icao": "LBSF", "terminal": "1", "gate": null, "baggage": null, "scheduled": "2026-07-11T15:55:00+00:00", "delay": null, "estimated": null, "actual": null, "estimated_runway": null, "actual_runway": null}, "airline": {"name": "Wizz Air", "iata": "W6", "icao": "WZZ"}, "flight": {"number": "4446", "iata": "W64446", "icao": "WZZ4446", "codeshared": null}, "aircraft": {"registration": null, "iata": null, "icao": null, "icao24": "4D2049"}, "live": null}, {"flight_date": "2026-07-11", "flight_status": "scheduled", "departure": {"airport": "Capodichino", "timezone": "Europe/Rome", "iata": "NAP", "icao": "LIRN", "terminal": null, "gate": "C19", "delay": null, "scheduled": "2026-07-11T13:35:00+00:00", "estimated": "2026-07-11T13:35:00+00:00", "actual": null, "estimated_runway": null, "actual_runway": null}, "arrival": {"airport": "Sofia", "timezone": "Europe/Sofia", "iata": "SOF", "icao": "LBSF", "terminal": "1", "gate": null, "baggage": null, "scheduled": "2026-07-11T16:20:00+00:00", "delay": null, "estimated": null, "actual": null, "estimated_runway": null, "actual_runway": null}, "airline": {"name": "Wizz Air", "iata": "W6", "icao": "WZZ"}, "flight": {"number": "4370", "iata": "W64370", "icao": "WZZ4370", "codeshared": null}, "aircraft": {"registration": null, "iata": null, "icao": null, "icao24": "4D2425"}, "live": null}, {"flight_date": "2026-07-11", "flight_status": "scheduled", "departure": {"airport": "Barajas", "timezone": "Europe/Madrid", "iata": "MAD", "icao": "LEMD", "terminal": "4", "gate": "733-", "delay": null, "scheduled": "2026-07-11T12:30:00+00:00", "estimated": "2026-07-11T12:30:00+00:00", "actual": null, "estimated_runway": null, "actual_runway": null}, "arrival": {"airport": "Sofia", "timezone": "Europe/Sofia", "iata": "SOF", "icao": "LBSF", "terminal": "2", "gate": null, "baggage": null, "scheduled": "2026-07-11T16:50:00+00:00", "delay": 14, "estimated": null, "actual": null, "estimated_runway": null, "actual_runway": null}, "airline": {"name": "Bulgaria Air", "iata": "FB", "icao": "LZB"}, "flight": {"number": "474", "iata": "FB474", "icao": "LZB474", "codeshared": null}, "aircraft": {"registration": null, "iata": null, "icao": null, "icao24": "452124"}, "live": null}, {"flight_date": "2026-07-11", "flight_status": "scheduled", "departure": {"airport": "Ciampino", "timezone": "Europe/Rome", "iata": "CIA", "icao": "LIRA", "terminal": null, "gate": "A", "delay": null, "scheduled": "2026-07-11T15:00:00+00:00", "estimated": "2026-07-11T15:00:00+00:00", "actual": null, "estimated_runway": null, "actual_runway": null}, "arrival": {"airport": "Sofia", "timezone": "Europe/Sofia", "iata": "SOF", "icao": "LBSF", "terminal": "2", "gate": null, "baggage": null, "scheduled": "2026-07-11T17:45:00+00:00", "delay": null, "estimated": null, "actual": null, "estimated_runway": null, "actual_runway": null}, "airline": {"name": "Ryanair", "iata": "FR", "icao": "RYR"}, "flight": {"number": "626", "iata": "FR626", "icao": "RYR626", "codeshared": null}, "aircraft": {"registration": null, "iata": null, "icao": null, "icao24": "48C121"}, "live": null}, {"flight_date": "2026-07-11", "flight_status": "scheduled", "departure": {"airport": "Frederic Chopin", "timezone": "Europe/Warsaw", "iata": "WAW", "icao": "EPWA", "terminal": null, "gate": null, "delay": null, "scheduled": "2026-07-11T14:55:00+00:00", "estimated": "2026-07-11T14:55:00+00:00", "actual": null, "estimated_runway": null, "actual_runway": null}, "arrival": {"airport": "Sofia", "timezone": "Europe/Sofia", "iata": "SOF", "icao": "LBSF", "terminal": "2", "gate": null, "baggage": null, "scheduled": "2026-07-11T18:00:00+00:00", "delay": null, "estimated": null, "actual": null, "estimated_runway": null, "actual_runway": null}, "airline": {"name": "LOT", "iata": "LO", "icao": "LOT"}, "flight": {"number": "633", "iata": "LO633", "icao": "LOT633", "codeshared": null}, "aircraft": null, "live": null}, {"flight_date": "2026-07-11", "flight_status": "scheduled", "departure": {"airport": "Frederic Chopin", "timezone": "Europe/Warsaw", "iata": "WAW", "icao": "EPWA", "terminal": null, "gate": null, "delay": null, "scheduled": "2026-07-11T14:55:00+00:00", "estimated": "2026-07-11T14:55:00+00:00", "actual": null, "estimated_runway": null, "actual_runway": null}, "arrival": {"airport": "Sofia", "timezone": "Europe/Sofia", "iata": "SOF", "icao": "LBSF", "terminal": "2", "gate": null, "baggage": null, "scheduled": "2026-07-11T18:00:00+00:00", "delay": null, "estimated": null, "actual": null, "estimated_runway": null, "actual_runway": null}, "airline": {"name": "TAP Air Portugal", "iata": "TP", "icao": "TAP"}, "flight": {"number": "7369", "iata": "TP7369", "icao": "TAP7369", "codeshared": {"airline_name": "lot", "airline_iata": "lo", "airline_icao": "lot", "flight_number": "633", "flight_iata": "lo633", "flight_icao": "lot633"}}, "aircraft": null, "live": null}, {"flight_date": "2026-07-11", "flight_status": "scheduled", "departure": {"airport": "Frederic Chopin", "timezone": "Europe/Warsaw", "iata": "WAW", "icao": "EPWA", "terminal": null, "gate": null, "delay": null, "scheduled": "2026-07-11T14:55:00+00:00", "estimated": "2026-07-11T14:55:00+00:00", "actual": null, "estimated_runway": null, "actual_runway": null}, "arrival": {"airport": "Sofia", "timezone": "Europe/Sofia", "iata": "SOF", "icao": "LBSF", "terminal": "2", "gate": null, "baggage": null, "scheduled": "2026-07-11T18:00:00+00:00", "delay": null, "estimated": null, "actual": null, "estimated_runway": null, "actual_runway": null}, "airline": {"name": "SAS", "iata": "SK", "icao": "SAS"}, "flight": {"number": "8132", "iata": "SK8132", "icao": "SAS8132", "codeshared": {"airline_name": "lot", "airline_iata": "lo", "airline_icao": "lot", "flight_number": "633", "flight_iata": "lo633", "flight_icao": "lot633"}}, "aircraft": null, "live": null}, {"flight_date": "2026-07-11", "flight_status": "scheduled", "departure": {"airport": "Eindhoven", "timezone": "Europe/Amsterdam", "iata": "EIN", "icao": "EHEH", "terminal": null, "gate": null, "delay": null, "scheduled": "2026-07-11T14:20:00+00:00", "estimated": "2026-07-11T14:20:00+00:00", "actual": null, "estimated_runway": null, "actual_runway": null}, "arrival": {"airport": "Sofia", "timezone": "Europe/Sofia", "iata": "SOF", "icao": "LBSF", "terminal": "1", "gate": null, "baggage": null, "scheduled": "2026-07-11T18:00:00+00:00", "delay": null, "estimated": null, "actual": null, "estimated_runway": null, "actual_runway": null}, "airline": {"name": "Wizz Air", "iata": "W6", "icao": "WZZ"}, "flight": {"number": "4326", "iata": "W64326", "icao": "WZZ4326", "codeshared": null}, "aircraft": {"registration": null, "iata": null, "icao": null, "icao24": "471D67"}, "live": null}]}